Workbook
Name Bollywood: Source_lists!$B$2:$B$13
Name data: Table16[]
Name Hollywood: Source_lists!$C$2:$C$10
Name Marvel_studios: Source_lists!$D$2:$D$9
Name release_date: Table11[#All]
Name release_date: Table11[#All]
Name release_date: Table11[#All]
Name release_date: Table11[#All]
Name Vinod_Chopra_Films: Source_lists!$D$42:$D$44

Sheet Source
A1: movie_id_title | B1: industry | C1: release_year | D1: imdb_rating | E1: studio | F1: language_id
A2: 101:K.G.F: Chapter 2 | B2: Bollywood | C2: 2022 | D2: 8.4 | E2: Hombale Films | F2: 3
A3: 102:Doctor Strange in the Multiverse of Madness | B3: Hollywood | C3: 2022 | D3: 7 | E3: Marvel Studios | F3: 5
A4: 103:Thor: The Dark World | B4: Hollywood | C4: 2013 | D4: 6.8 | E4: Marvel Studios | F4: 5
A5: 104:Thor: Ragnarok | B5: Hollywood | C5: 2017 | D5: 7.9 | E5: Marvel Studios | F5: 5
A6: 105:Thor: Love and Thunder | B6: Hollywood | C6: 2022 | D6: 6.8 | E6: Marvel Studios | F6: 5
A7: 106:Sholay | B7: Bollywood | C7: 1975 | D7: 8.1 | E7: United Producers | F7: 1
A8: 107:Dilwale Dulhania Le Jayenge | B8: Bollywood | C8: 1995 | D8: 8 | E8: Yash Raj Films | F8: 1
A9: 108: 3 Idiots | B9: Bollywood | C9: 2009 | D9: 8.4 | E9: Vinod Chopra Films | F9: 1
A10: 109:Kabhi Khushi Kabhie Gham | B10: Bollywood | C10: 2001 | D10: 7.4 | E10: Dharma Productions | F10: 1
A11: 110:Bajirao Mastani | B11: Bollywood | C11: 2015 | D11: 7.2 | F11: 1
A12: 111: The Shawshank Redemption | B12: Hollywood | C12: 1994 | D12: 9.3 | E12: Castle Rock Entertainment | F12: 5
A13: 112:Inception | B13: Hollywood | C13: 2010 | D13: 8.8 | E13: Warner Bros. Pictures | F13: 5
A14: 113:Interstellar | B14: Hollywood | C14: 2014 | D14: 8.6 | E14: Warner Bros. Pictures | F14: 5
A15: 115:The Pursuit of Happyness | B15: Hollywood | C15: 2006 | D15: 8 | E15: Columbia Pictures | F15: 5
A16: 116:Gladiator | B16: Hollywood | C16: 2000 | D16: 8.5 | E16: Universal Pictures | F16: 5
A17: 117:Titanic | B17: Hollywood | C17: 1997 | D17: 7.9 | E17: Paramount Pictures | F17: 5
A18: 118:It's a Wonderful Life | B18: Hollywood | C18: 1946 | D18: 8.6 | E18: Liberty Films | F18: 5
A19: 119:Avatar | B19: Hollywood | C19: 2009 | D19: 7.8 | E19: 20th Century Fox | F19: 5
A20: 120:The Godfather | B20: Hollywood | C20: 1972 | D20: 9.2 | E20: Paramount Pictures | F20: 5
A21: 121:The Dark Knight | B21: Hollywood | C21: 2008 | D21: 9 | E21: Syncopy | F21: 5
A22: 122:Schindler's List | B22: Hollywood | C22: 1993 | D22: 9 | E22: Universal Pictures | F22: 5
A23: 123:Jurassic Park | B23: Hollywood | C23: 1993 | D23: 8.2 | E23: Universal Pictures | F23: 5
A24: 124:Parasite | B24: Hollywood | C24: 2019 | D24: 8.5 | F24: 5
A25: 125:Avengers: Endgame | B25: Hollywood | C25: 2019 | D25: 8.4 | E25: Marvel Studios | F25: 5
A26: 126:Avengers: Infinity War | B26: Hollywood | C26: 2018 | D26: 8.4 | E26: Marvel Studios | F26: 5
A27: 127:Pather Panchali | B27: Bollywood | C27: 1955 | D27: 8.3 | E27: Government of West Bengal | F27: 7
A28: 128:Taare Zameen Par | B28: Bollywood | C28: 2007 | D28: 8.3 | F28: 1
A29: 129:Munna Bhai M.B.B.S. | B29: Bollywood | C29: 2003 | D29: 8.1 | E29: Vinod Chopra Productions | F29: 1
A30: 124:Parasite | B30: Hollywood | C30: 2019 | D30: 8.5 | F30: 5
A31: 105:Thor: Love and Thunder | B31: Hollywood | C31: 2022 | D31: 6.8 | E31: Marvel Studios | F31: 5
A32: 130:PK | B32: Bollywood | C32: 2014 | D32: 8.1 | E32: Vinod Chopra Films | F32: 1
A33: 131:Sanju | B33: Bollywood | C33: 2018 | D33: NULL | E33: Vinod Chopra Films | F33: 1
A34: 132:Pushpa: The Rise - Part 1 | B34: Bollywood | C34: 2021 | D34: 7.6 | E34: Mythri Movie Makers | F34: 2
A35: 133:RRR | B35: Bollywood | C35: 2022 | D35: 8 | E35: DVV Entertainment | F35: 2
A36: 134:Baahubali: The Beginning | B36: Bollywood | C36: 2015 | D36: 8 | E36: Arka Media Works | F36: 2
A37: 135:The Kashmir Files | B37: Bollywood | C37: 2022 | D37: 8.3 | E37: Zee Studios | F37: 1
A38: 136:Bajrangi Bhaijaan | B38: Bollywood | C38: 2015 | D38: 8.1 | E38: Salman Khan Films | F38: 1
A39: 137:Captain America: The First Avenger | B39: Hollywood | C39: 2011 | D39: 6.9 | E39: Marvel Studios | F39: 5
A40: 138:Captain America: The Winter Soldier | B40: Hollywood | C40: 2014 | D40: 7.8 | E40: Marvel Studios | F40: 5
A41: 139:Race 3 | B41: Bollywood | C41: 2018 | D41: 1.9 | E41: Salman Khan Films | F41: 1
A42: 140:Shershaah | B42: Bollywood | C42: 2021 | D42: 8.4 | E42: Dharma Productions | F42: 1

Sheet Financials (2)
A1: movie_id | B1: budget | C1: revenue | D1: unit | E1: currency
A2: 101 | B2: 1 | C2: 12.5 | D2: Billions | E2: INR
A3: 102 | B3: 200 | C3: 954.8 | D3: Millions | E3: USD
A4: 103 | B4: 165 | C4: 644.8 | D4: Millions | E4: USD
A5: 104 | B5: 180 | C5: 854 | D5: Millions | E5: USD
A6: 105 | B6: 250 | C6: 670 | D6: Millions | E6: USD
A7: 107 | B7: 400 | C7: 2000 | D7: Millions | E7: INR
A8: 108 | B8: 550 | C8: 4000 | D8: Millions | E8: INR
A9: 109 | B9: 390 | C9: 1360 | D9: Millions | E9: INR
A10: 110 | B10: 1.4 | C10: 3.5 | D10: Billions | E10: INR
A11: 111 | B11: 25 | C11: 73.3 | D11: Millions | E11: USD
A12: 113 | B12: 165 | C12: 701.8 | D12: Millions | E12: USD
A13: 114 | B13: 205 | C13: 365.3 | D13: Millions | E13: USD
... A41: 412 | B41: 160 | C41: 836.8 | D41: Millions | E41: USD

Sheet financials
A1: movie_id | B1: budget | C1: revenue | D1: unit | E1: currency
A2: 101 | B2: 1 | C2: 12.5 | D2: Billions | E2: INR
A3: 102 | B3: 200 | C3: 954.8 | D3: Millions | E3: USD
A4: 103 | B4: 165 | C4: 644.8 | D4: Millions | E4: USD
A5: 104 | B5: 180 | C5: 854 | D5: Millions | E5: USD
A6: 105 | B6: 250 | C6: 670 | D6: Millions | E6: USD
A7: 107 | B7: 400 | C7: 2000 | D7: Millions | E7: INR
A8: 108 | B8: 550 | C8: 4000 | D8: Millions | E8: INR
A9: 109 | B9: 390 | C9: 1360 | D9: Millions | E9: INR
A10: 110 | B10: 1.4 | C10: 3.5 | D10: Billions | E10: INR
A11: 111 | B11: 25 | C11: 73.3 | D11: Millions | E11: USD
A12: 113 | B12: 165 | C12: 701.8 | D12: Millions | E12: USD
A13: 114 | B13: 205 | C13: 365.3 | D13: Millions | E13: USD
... A41: 412 | B41: 160 | C41: 836.8 | D41: Millions | E41: USD

Sheet release_date
A1: Title | B1: release_date
A2: K.G.F: Chapter 2 | B2: 44665
A3: Doctor Strange in the Multiverse of Madness | B3: 44687
A4: Thor: The Dark World | B4: 41586
A5: Thor: Ragnarok | B5: 43042
A6: Thor: Love and Thunder | B6: 44750
A7: Sholay | B7: 27621
A8: Dilwale Dulhania Le Jayenge | B8: 34992
A9: 3 Idiots | B9: 40172
A10: Kabhi Khushi Kabhie Gham | B10: 37239
A11: Bajirao Mastani | B11: 42356
A12: The Shawshank Redemption | B12: 34600
A13: Inception | B13: 40489
... A42: Shershaah | B42: 44420

Sheet DAY 1
A1: Movie_id | B1: Title | C1: release_year | D1: industry | E1: release_year2 | F1: imdb_rating | G1: studio | H1: language_id | I1: Xlookup Budget | J1: Vlookup Budget | K1: Revenue | L1: unit | M1: status
A2: 101 | B2: K.G.F: Chapter 2 | C2: 2022 | D2: Bollywood | E2: 2022 | F2: 8.4 | G2: Hombale Films | H2: 3 | I2: =_xlfn.XLOOKUP(Movies_1[[#This Row],[Movie_id]],Financials[movie_id],Financials[budget],"not Avialable") -> 1 | J2: =VLOOKUP(Movies_1[[#This Row],[Movie_id]],Financials[],2,FALSE) -> 1 | K2: =_xlfn.XLOOKUP(Movies_1[[#This Row],[Movie_id]],Financials[movie_id],Financials[revenue],"not avialable") -> 12.5 | L2: =_xlfn.XLOOKUP(Movies_1[[#This Row],[Movie_id]],Financials[movie_id],Financials[unit],TRUE) -> Billions | M2: =IF(ISNUMBER(I2),"Matched","Missing Finance Data") -> Matched
A3: 102 | B3: Doctor Strange in the Multiverse of Madness | C3: 2022 | D3: Hollywood | E3: 2022 | F3: 7 | G3: Marvel Studios | H3: 5 | I3: =_xlfn.XLOOKUP(Movies_1[[#This Row],[Movie_id]],Financials[movie_id],Financials[budget],"not Avialable") -> 200 | J3: =VLOOKUP(Movies_1[[#This Row],[Movie_id]],Financials[],2,FALSE) -> 200 | K3: =_xlfn.XLOOKUP(Movies_1[[#This Row],[Movie_id]],Financials[movie_id],Financials[revenue],"not avialable") -> 954.8 | L3: =_xlfn.XLOOKUP(Movies_1[[#This Row],[Movie_id]],Financials[movie_id],Financials[unit],TRUE) -> Millions | M3: =IF(ISNUMBER(I3),"Matched","Missing Finance Data") -> Matched
A4: 103 | B4: Thor: The Dark World | C4: 2013 | D4: Hollywood | E4: 2013 | F4: 6.8 | G4: Marvel Studios | H4: 5 | I4: =_xlfn.XLOOKUP(Movies_1[[#This Row],[Movie_id]],Financials[movie_id],Financials[budget],"not Avialable") -> 165 | J4: =VLOOKUP(Movies_1[[#This Row],[Movie_id]],Financials[],2,FALSE) -> 165 | K4: =_xlfn.XLOOKUP(Movies_1[[#This Row],[Movie_id]],Financials[movie_id],Financials[revenue],"not avialable") -> 644.8 | L4: =_xlfn.XLOOKUP(Movies_1[[#This Row],[Movie_id]],Financials[movie_id],Financials[unit],TRUE) -> Millions | M4: =IF(ISNUMBER(I4),"Matched","Missing Finance Data") -> Matched
A5: 104 | B5: Thor: Ragnarok | C5: 2017 | D5: Hollywood | E5: 2017 | F5: 7.9 | G5: Marvel Studios | H5: 5 | I5: =_xlfn.XLOOKUP(Movies_1[[#This Row],[Movie_id]],Financials[movie_id],Financials[budget],"not Avialable") -> 180 | J5: =VLOOKUP(Movies_1[[#This Row],[Movie_id]],Financials[],2,FALSE) -> 180 | K5: =_xlfn.XLOOKUP(Movies_1[[#This Row],[Movie_id]],Financials[movie_id],Financials[revenue],"not avialable") -> 854 | L5: =_xlfn.XLOOKUP(Movies_1[[#This Row],[Movie_id]],Financials[movie_id],Financials[unit],TRUE) -> Millions | M5: =IF(ISNUMBER(I5),"Matched","Missing Finance Data") -> Matched
A6: 105 | B6: Thor: Love and Thunder | C6: 2022 | D6: Hollywood | E6: 2022 | F6: 6.8 | G6: Marvel Studios | H6: 5 | I6: =_xlfn.XLOOKUP(Movies_1[[#This Row],[Movie_id]],Financials[movie_id],Financials[budget],"not Avialable") -> 250 | J6: =VLOOKUP(Movies_1[[#This Row],[Movie_id]],Financials[],2,FALSE) -> 250 | K6: =_xlfn.XLOOKUP(Movies_1[[#This Row],[Movie_id]],Financials[movie_id],Financials[revenue],"not avialable") -> 670 | L6: =_xlfn.XLOOKUP(Movies_1[[#This Row],[Movie_id]],Financials[movie_id],Financials[unit],TRUE) -> Millions | M6: =IF(ISNUMBER(I6),"Matched","Missing Finance Data") -> Matched
A7: 106 | B7: Sholay | C7: 2022 | D7: Bollywood | E7: 1975 | F7: 8.1 | G7: United Producers | H7: 1 | I7: =_xlfn.XLOOKUP(Movies_1[[#This Row],[Movie_id]],Financials[movie_id],Financials[budget],"not Avialable") -> not Avialable | J7: =VLOOKUP(Movies_1[[#This Row],[Movie_id]],Financials[],2,FALSE) -> #N/A | K7: =_xlfn.XLOOKUP(Movies_1[[#This Row],[Movie_id]],Financials[movie_id],Financials[revenue],"not avialable") -> not avialable | L7: =_xlfn.XLOOKUP(Movies_1[[#This Row],[Movie_id]],Financials[movie_id],Financials[unit],TRUE) -> TRUE | M7: =IF(ISNUMBER(I7),"Matched","Missing Finance Data") -> Missing Finance Data
A8: 107 | B8: Dilwale Dulhania Le Jayenge | C8: 2022 | D8: Bollywood | E8: 1995 | F8: 8 | G8: Yash Raj Films | H8: 1 | I8: =_xlfn.XLOOKUP(Movies_1[[#This Row],[Movie_id]],Financials[movie_id],Financials[budget],"not Avialable") -> 400 | J8: =VLOOKUP(Movies_1[[#This Row],[Movie_id]],Financials[],2,FALSE) -> 400 | K8: =_xlfn.XLOOKUP(Movies_1[[#This Row],[Movie_id]],Financials[movie_id],Financials[revenue],"not avialable") -> 2000 | L8: =_xlfn.XLOOKUP(Movies_1[[#This Row],[Movie_id]],Financials[movie_id],Financials[unit],TRUE) -> Millions | M8: =IF(ISNUMBER(I8),"Matched","Missing Finance Data") -> Matched
A9: 108 | B9: 3 Idiots | C9: 2022 | D9: Bollywood | E9: 2009 | F9: 8.4 | G9: Vinod Chopra Films | H9: 1 | I9: =_xlfn.XLOOKUP(Movies_1[[#This Row],[Movie_id]],Financials[movie_id],Financials[budget],"not Avialable") -> 550 | J9: =VLOOKUP(Movies_1[[#This Row],[Movie_id]],Financials[],2,FALSE) -> 550 | K9: =_xlfn.XLOOKUP(Movies_1[[#This Row],[Movie_id]],Financials[movie_id],Financials[revenue],"not avialable") -> 4000 | L9: =_xlfn.XLOOKUP(Movies_1[[#This Row],[Movie_id]],Financials[movie_id],Financials[unit],TRUE) -> Millions | M9: =IF(ISNUMBER(I9),"Matched","Missing Finance Data") -> Matched
A10: 109 | B10: Kabhi Khushi Kabhie Gham | C10: 1975 | D10: Bollywood | E10: 2001 | F10: 7.4 | G10: Dharma Productions | H10: 1 | I10: =_xlfn.XLOOKUP(Movies_1[[#This Row],[Movie_id]],Financials[movie_id],Financials[budget],"not Avialable") -> 390 | J10: =VLOOKUP(Movies_1[[#This Row],[Movie_id]],Financials[],2,FALSE) -> 390 | K10: =_xlfn.XLOOKUP(Movies_1[[#This Row],[Movie_id]],Financials[movie_id],Financials[revenue],"not avialable") -> 1360 | L10: =_xlfn.XLOOKUP(Movies_1[[#This Row],[Movie_id]],Financials[movie_id],Financials[unit],TRUE) -> Millions | M10: =IF(ISNUMBER(I10),"Matched","Missing Finance Data") -> Matched
A11: 110 | B11: Bajirao Mastani | C11: 1995 | D11: Bollywood | E11: 2015 | F11: 7.2 | G11: Not Avialable | H11: 1 | I11: =_xlfn.XLOOKUP(Movies_1[[#This Row],[Movie_id]],Financials[movie_id],Financials[budget],"not Avialable") -> 1.4 | J11: =VLOOKUP(Movies_1[[#This Row],[Movie_id]],Financials[],2,FALSE) -> 1.4 | K11: =_xlfn.XLOOKUP(Movies_1[[#This Row],[Movie_id]],Financials[movie_id],Financials[revenue],"not avialable") -> 3.5 | L11: =_xlfn.XLOOKUP(Movies_1[[#This Row],[Movie_id]],Financials[movie_id],Financials[unit],TRUE) -> Billions | M11: =IF(ISNUMBER(I11),"Matched","Missing Finance Data") -> Matched
A12: 111 | B12: The Shawshank Redemption | C12: 2009 | D12: Hollywood | E12: 1994 | F12: 9.3 | G12: Castle Rock Entertainment | H12: 5 | I12: =_xlfn.XLOOKUP(Movies_1[[#This Row],[Movie_id]],Financials[movie_id],Financials[budget],"not Avialable") -> 25 | J12: =VLOOKUP(Movies_1[[#This Row],[Movie_id]],Financials[],2,FALSE) -> 25 | K12: =_xlfn.XLOOKUP(Movies_1[[#This Row],[Movie_id]],Financials[movie_id],Financials[revenue],"not avialable") -> 73.3 | L12: =_xlfn.XLOOKUP(Movies_1[[#This Row],[Movie_id]],Financials[movie_id],Financials[unit],TRUE) -> Millions | M12: =IF(ISNUMBER(I12),"Matched","Missing Finance Data") -> Matched
A13: 112 | B13: Inception | C13: 2001 | D13: Hollywood | E13: 2010 | F13: 8.8 | G13: Warner Bros. Pictures | H13: 5 | I13: =_xlfn.XLOOKUP(Movies_1[[#This Row],[Movie_id]],Financials[movie_id],Financials[budget],"not Avialable") -> not Avialable | J13: =VLOOKUP(Movies_1[[#This Row],[Movie_id]],Financials[],2,FALSE) -> #N/A | K13: =_xlfn.XLOOKUP(Movies_1[[#This Row],[Movie_id]],Financials[movie_id],Financials[revenue],"not avialable") -> not avialable | L13: =_xlfn.XLOOKUP(Movies_1[[#This Row],[Movie_id]],Financials[movie_id],Financials[unit],TRUE) -> TRUE | M13: =IF(ISNUMBER(I13),"Matched","Missing Finance Data") -> Missing Finance Data
... A42: 140 | B42: Shershaah | C42: 2021 | D42: Bollywood | E42: 2021 | F42: 8.4 | G42: Dharma Productions | H42: 1 | I42: =_xlfn.XLOOKUP(Movies_1[[#This Row],[Movie_id]],Financials[movie_id],Financials[budget],"not Avialable") -> 500 | J42: =VLOOKUP(Movies_1[[#This Row],[Movie_id]],Financials[],2,FALSE) -> 500 | K42: =_xlfn.XLOOKUP(Movies_1[[#This Row],[Movie_id]],Financials[movie_id],Financials[revenue],"not avialable") -> 950 | L42: =_xlfn.XLOOKUP(Movies_1[[#This Row],[Movie_id]],Financials[movie_id],Financials[unit],TRUE) -> Millions | M42: =IF(ISNUMBER(I42),"Matched","Missing Finance Data") -> Matched

Sheet DAY 2
A1: movie_id | B1: budget | C1: revenue | D1: unit | E1: currency | H1: Sales | I1: Tax rate | J1: Tax amount | M1: * | N1: 2 | O1: 3
A2: 101 | B2: 1 | C2: 12.5 | D2: Billions | E2: INR | H2: 1000 | I2: 0.18 | J2: =H2*$I$2 -> 180 | L2: 1 | M2: 10 | N2: =$M2*$N$1 -> 20 | O2: =$L2*$O$1 -> 3
A3: 102 | B3: 200 | C3: 954.8 | D3: Millions | E3: USD | H3: 1500 | J3: =H3*$I$2 -> 270 | L3: 2 | M3: 20 | N3: =$M3*$N$1 -> 40 | O3: =$L3*$O$1 -> 6
A4: 103 | B4: 165 | C4: 644.8 | D4: Millions | E4: USD | H4: 2000 | J4: =H4*$I$2 -> 360 | L4: 3 | M4: 30 | N4: =$M4*$N$1 -> 60 | O4: =$L4*$O$1 -> 9
A5: 104 | B5: 180 | C5: 854 | D5: Millions | E5: USD | H5: 3000 | J5: =H5*$I$2 -> 540 | L5: 4 | M5: 40 | N5: =$M5*$N$1 -> 80 | O5: =$L5*$O$1 -> 12
A6: 105 | B6: 250 | C6: 670 | D6: Millions | E6: USD | L6: 5 | O6: =$L6*$O$1 -> 15
A7: 107 | B7: 400 | C7: 2000 | D7: Millions | E7: INR | L7: 6 | O7: =$L7*$O$1 -> 18
A8: 108 | B8: 550 | C8: 4000 | D8: Millions | E8: INR | L8: 7 | O8: =$L8*$O$1 -> 21
A9: 109 | B9: 390 | C9: 1360 | D9: Millions | E9: INR | L9: 8 | O9: =$L9*$O$1 -> 24
A10: 110 | B10: 1.4 | C10: 3.5 | D10: Billions | E10: INR | L10: 9 | O10: =$L10*$O$1 -> 27
A11: 111 | B11: 25 | C11: 73.3 | D11: Millions | E11: USD | L11: 10 | O11: =$L11*$O$1 -> 30
A12: 113 | B12: 165 | C12: 701.8 | D12: Millions | E12: USD
A13: 114 | B13: 205 | C13: 365.3 | D13: Millions | E13: USD
A14: 115 | B14: 55 | C14: 307.1 | D14: Millions | E14: USD
A15: 116 | B15: 103 | C15: 460.5 | D15: Millions | E15: USD
A16: 117 | B16: 200 | C16: 2202 | D16: Millions | E16: USD
A17: 118 | B17: 3.18 | C17: 3.3 | D17: Millions | E17: USD
A18: 119 | B18: 237 | C18: 2847 | D18: Millions | E18: USD
A19: 120 | B19: 7.2 | C19: 291 | D19: Millions | E19: USD
A20: 121 | B20: 185 | C20: 1006 | D20: Millions | E20: USD
A21: 122 | B21: 22 | C21: 322.2 | D21: Millions | E21: USD
A22: 123 | B22: 63 | C22: 1046 | D22: Millions | E22: USD
A23: 124 | B23: 15.5 | C23: 263.1 | D23: Millions | E23: USD
... A41: 412 | B41: 160 | C41: 836.8 | D41: Millions | E41: USD

Sheet DAY 3
A1: Movie_id | B1: Title | C1: industry | D1: release_year | E1: imdb_rating | F1: studio | G1: language_id | H1: budget | I1: revenue | J1: unit | K1: currency | L1: release_date | M1: Movie_performance | N1: Rating_category | O1: Budget_category
A2: 101 | B2: K.G.F: Chapter 2 | C2: Bollywood | D2: 2022 | E2: 8.4 | F2: Hombale Films | G2: 3 | H2: 1 | I2: 12.5 | J2: Billions | K2: INR | L2: 44665 | M2: {=_xlfn.IFS( Movie_financials[[#This Row],[revenue]]<500,"Average", Movie_financials[[#This Row],[revenue]]<=1000,"Hit", TRUE,"Blockbuster")} -> Average | N2: {=_xlfn.IFS(Movie_financials[[#This Row],[imdb_rating]]<7,"Average",Movie_financials[[#This Row],[imdb_rating]]<=8.5,"Good",TRUE,"Excellent")} -> Good | O2: {=_xlfn.IFS(Movie_financials[[#This Row],[budget]]<50,"Low budget",Movie_financials[[#This Row],[budget]]<=150,"Medium budget",TRUE,"High budget")} -> Low budget
A3: 102 | B3: Doctor Strange in the Multiverse of Madness | C3: Hollywood | D3: 2022 | E3: 7 | F3: Marvel Studios | G3: 5 | H3: 200 | I3: 954.8 | J3: Millions | K3: USD | L3: 44687 | M3: {=_xlfn.IFS( Movie_financials[[#This Row],[revenue]]<500,"Average", Movie_financials[[#This Row],[revenue]]<=1000,"Hit", TRUE,"Blockbuster")} -> Hit | N3: {=_xlfn.IFS(Movie_financials[[#This Row],[imdb_rating]]<7,"Average",Movie_financials[[#This Row],[imdb_rating]]<=8.5,"Good",TRUE,"Excellent")} -> Good | O3: {=_xlfn.IFS(Movie_financials[[#This Row],[budget]]<50,"Low budget",Movie_financials[[#This Row],[budget]]<=150,"Medium budget",TRUE,"High budget")} -> High budget
A4: 103 | B4: Thor: The Dark World | C4: Hollywood | D4: 2013 | E4: 6.8 | F4: Marvel Studios | G4: 5 | H4: 165 | I4: 644.8 | J4: Millions | K4: USD | L4: 41586 | M4: {=_xlfn.IFS( Movie_financials[[#This Row],[revenue]]<500,"Average", Movie_financials[[#This Row],[revenue]]<=1000,"Hit", TRUE,"Blockbuster")} -> Hit | N4: {=_xlfn.IFS(Movie_financials[[#This Row],[imdb_rating]]<7,"Average",Movie_financials[[#This Row],[imdb_rating]]<=8.5,"Good",TRUE,"Excellent")} -> Average | O4: {=_xlfn.IFS(Movie_financials[[#This Row],[budget]]<50,"Low budget",Movie_financials[[#This Row],[budget]]<=150,"Medium budget",TRUE,"High budget")} -> High budget
A5: 104 | B5: Thor: Ragnarok | C5: Hollywood | D5: 2017 | E5: 7.9 | F5: Marvel Studios | G5: 5 | H5: 180 | I5: 854 | J5: Millions | K5: USD | L5: 43042 | M5: {=_xlfn.IFS( Movie_financials[[#This Row],[revenue]]<500,"Average", Movie_financials[[#This Row],[revenue]]<=1000,"Hit", TRUE,"Blockbuster")} -> Hit | N5: {=_xlfn.IFS(Movie_financials[[#This Row],[imdb_rating]]<7,"Average",Movie_financials[[#This Row],[imdb_rating]]<=8.5,"Good",TRUE,"Excellent")} -> Good | O5: {=_xlfn.IFS(Movie_financials[[#This Row],[budget]]<50,"Low budget",Movie_financials[[#This Row],[budget]]<=150,"Medium budget",TRUE,"High budget")} -> High budget
A6: 105 | B6: Thor: Love and Thunder | C6: Hollywood | D6: 2022 | E6: 6.8 | F6: Marvel Studios | G6: 5 | H6: 250 | I6: 670 | J6: Millions | K6: USD | L6: 44750 | M6: {=_xlfn.IFS( Movie_financials[[#This Row],[revenue]]<500,"Average", Movie_financials[[#This Row],[revenue]]<=1000,"Hit", TRUE,"Blockbuster")} -> Hit | N6: {=_xlfn.IFS(Movie_financials[[#This Row],[imdb_rating]]<7,"Average",Movie_financials[[#This Row],[imdb_rating]]<=8.5,"Good",TRUE,"Excellent")} -> Average | O6: {=_xlfn.IFS(Movie_financials[[#This Row],[budget]]<50,"Low budget",Movie_financials[[#This Row],[budget]]<=150,"Medium budget",TRUE,"High budget")} -> High budget
A7: 106 | B7: Sholay | C7: Bollywood | D7: 1975 | E7: 8.1 | F7: United Producers | G7: 1 | L7: 27621 | M7: {=_xlfn.IFS( Movie_financials[[#This Row],[revenue]]<500,"Average", Movie_financials[[#This Row],[revenue]]<=1000,"Hit", TRUE,"Blockbuster")} -> Average | N7: {=_xlfn.IFS(Movie_financials[[#This Row],[imdb_rating]]<7,"Average",Movie_financials[[#This Row],[imdb_rating]]<=8.5,"Good",TRUE,"Excellent")} -> Good | O7: {=_xlfn.IFS(Movie_financials[[#This Row],[budget]]<50,"Low budget",Movie_financials[[#This Row],[budget]]<=150,"Medium budget",TRUE,"High budget")} -> Low budget
A8: 107 | B8: Dilwale Dulhania Le Jayenge | C8: Bollywood | D8: 1995 | E8: 8 | F8: Yash Raj Films | G8: 1 | H8: 400 | I8: 2000 | J8: Millions | K8: INR | L8: 34992 | M8: {=_xlfn.IFS( Movie_financials[[#This Row],[revenue]]<500,"Average", Movie_financials[[#This Row],[revenue]]<=1000,"Hit", TRUE,"Blockbuster")} -> Blockbuster | N8: {=_xlfn.IFS(Movie_financials[[#This Row],[imdb_rating]]<7,"Average",Movie_financials[[#This Row],[imdb_rating]]<=8.5,"Good",TRUE,"Excellent")} -> Good | O8: {=_xlfn.IFS(Movie_financials[[#This Row],[budget]]<50,"Low budget",Movie_financials[[#This Row],[budget]]<=150,"Medium budget",TRUE,"High budget")} -> High budget
A9: 108 | B9: 3 Idiots | C9: Bollywood | D9: 2009 | E9: 8.4 | F9: Vinod Chopra Films | G9: 1 | H9: 550 | I9: 4000 | J9: Millions | K9: INR | L9: 40172 | M9: {=_xlfn.IFS( Movie_financials[[#This Row],[revenue]]<500,"Average", Movie_financials[[#This Row],[revenue]]<=1000,"Hit", TRUE,"Blockbuster")} -> Blockbuster | N9: {=_xlfn.IFS(Movie_financials[[#This Row],[imdb_rating]]<7,"Average",Movie_financials[[#This Row],[imdb_rating]]<=8.5,"Good",TRUE,"Excellent")} -> Good | O9: {=_xlfn.IFS(Movie_financials[[#This Row],[budget]]<50,"Low budget",Movie_financials[[#This Row],[budget]]<=150,"Medium budget",TRUE,"High budget")} -> High budget
A10: 109 | B10: Kabhi Khushi Kabhie Gham | C10: Bollywood | D10: 2001 | E10: 7.4 | F10: Dharma Productions | G10: 1 | H10: 390 | I10: 1360 | J10: Millions | K10: INR | L10: 37239 | M10: {=_xlfn.IFS( Movie_financials[[#This Row],[revenue]]<500,"Average", Movie_financials[[#This Row],[revenue]]<=1000,"Hit", TRUE,"Blockbuster")} -> Blockbuster | N10: {=_xlfn.IFS(Movie_financials[[#This Row],[imdb_rating]]<7,"Average",Movie_financials[[#This Row],[imdb_rating]]<=8.5,"Good",TRUE,"Excellent")} -> Good | O10: {=_xlfn.IFS(Movie_financials[[#This Row],[budget]]<50,"Low budget",Movie_financials[[#This Row],[budget]]<=150,"Medium budget",TRUE,"High budget")} -> High budget
A11: 110 | B11: Bajirao Mastani | C11: Bollywood | D11: 2015 | E11: 7.2 | F11: Not Avialable | G11: 1 | H11: 1 | I11: 3.5 | J11: Billions | K11: INR | L11: 42356 | M11: {=_xlfn.IFS( Movie_financials[[#This Row],[revenue]]<500,"Average", Movie_financials[[#This Row],[revenue]]<=1000,"Hit", TRUE,"Blockbuster")} -> Average | N11: {=_xlfn.IFS(Movie_financials[[#This Row],[imdb_rating]]<7,"Average",Movie_financials[[#This Row],[imdb_rating]]<=8.5,"Good",TRUE,"Excellent")} -> Good | O11: {=_xlfn.IFS(Movie_financials[[#This Row],[budget]]<50,"Low budget",Movie_financials[[#This Row],[budget]]<=150,"Medium budget",TRUE,"High budget")} -> Low budget
A12: 111 | B12: The Shawshank Redemption | C12: Hollywood | D12: 1994 | E12: 9.3 | F12: Castle Rock Entertainment | G12: 5 | H12: 25 | I12: 73.3 | J12: Millions | K12: USD | L12: 34600 | M12: {=_xlfn.IFS( Movie_financials[[#This Row],[revenue]]<500,"Average", Movie_financials[[#This Row],[revenue]]<=1000,"Hit", TRUE,"Blockbuster")} -> Average | N12: {=_xlfn.IFS(Movie_financials[[#This Row],[imdb_rating]]<7,"Average",Movie_financials[[#This Row],[imdb_rating]]<=8.5,"Good",TRUE,"Excellent")} -> Excellent | O12: {=_xlfn.IFS(Movie_financials[[#This Row],[budget]]<50,"Low budget",Movie_financials[[#This Row],[budget]]<=150,"Medium budget",TRUE,"High budget")} -> Low budget
A13: 113 | B13: Interstellar | C13: Hollywood | D13: 2014 | E13: 8.6 | F13: Warner Bros. Pictures | G13: 5 | H13: 165 | I13: 701.8 | J13: Millions | K13: USD | L13: 41836 | M13: {=_xlfn.IFS( Movie_financials[[#This Row],[revenue]]<500,"Average", Movie_financials[[#This Row],[revenue]]<=1000,"Hit", TRUE,"Blockbuster")} -> Hit | N13: {=_xlfn.IFS(Movie_financials[[#This Row],[imdb_rating]]<7,"Average",Movie_financials[[#This Row],[imdb_rating]]<=8.5,"Good",TRUE,"Excellent")} -> Excellent | O13: {=_xlfn.IFS(Movie_financials[[#This Row],[budget]]<50,"Low budget",Movie_financials[[#This Row],[budget]]<=150,"Medium budget",TRUE,"High budget")} -> High budget
A14: 112 | B14: Inception | C14: Hollywood | D14: 2010 | E14: 8.8 | F14: Warner Bros. Pictures | G14: 5 | L14: 40489 | M14: {=_xlfn.IFS( Movie_financials[[#This Row],[revenue]]<500,"Average", Movie_financials[[#This Row],[revenue]]<=1000,"Hit", TRUE,"Blockbuster")} -> Average | N14: {=_xlfn.IFS(Movie_financials[[#This Row],[imdb_rating]]<7,"Average",Movie_financials[[#This Row],[imdb_rating]]<=8.5,"Good",TRUE,"Excellent")} -> Excellent | O14: {=_xlfn.IFS(Movie_financials[[#This Row],[budget]]<50,"Low budget",Movie_financials[[#This Row],[budget]]<=150,"Medium budget",TRUE,"High budget")} -> Low budget
A15: 115 | B15: The Pursuit of Happyness | C15: Hollywood | D15: 2006 | E15: 8 | F15: Columbia Pictures | G15: 5 | H15: 55 | I15: 307.1 | J15: Millions | K15: USD | L15: 39066 | M15: {=_xlfn.IFS( Movie_financials[[#This Row],[revenue]]<500,"Average", Movie_financials[[#This Row],[revenue]]<=1000,"Hit", TRUE,"Blockbuster")} -> Average | N15: {=_xlfn.IFS(Movie_financials[[#This Row],[imdb_rating]]<7,"Average",Movie_financials[[#This Row],[imdb_rating]]<=8.5,"Good",TRUE,"Excellent")} -> Good | O15: {=_xlfn.IFS(Movie_financials[[#This Row],[budget]]<50,"Low budget",Movie_financials[[#This Row],[budget]]<=150,"Medium budget",TRUE,"High budget")} -> Medium budget
A16: 116 | B16: Gladiator | C16: Hollywood | D16: 2000 | E16: 8.5 | F16: Universal Pictures | G16: 5 | H16: 103 | I16: 460.5 | J16: Millions | K16: USD | L16: 36651 | M16: {=_xlfn.IFS( Movie_financials[[#This Row],[revenue]]<500,"Average", Movie_financials[[#This Row],[revenue]]<=1000,"Hit", TRUE,"Blockbuster")} -> Average | N16: {=_xlfn.IFS(Movie_financials[[#This Row],[imdb_rating]]<7,"Average",Movie_financials[[#This Row],[imdb_rating]]<=8.5,"Good",TRUE,"Excellent")} -> Good | O16: {=_xlfn.IFS(Movie_financials[[#This Row],[budget]]<50,"Low budget",Movie_financials[[#This Row],[budget]]<=150,"Medium budget",TRUE,"High budget")} -> Medium budget
A17: 117 | B17: Titanic | C17: Hollywood | D17: 1997 | E17: 7.9 | F17: Paramount Pictures | G17: 5 | H17: 200 | I17: 2202 | J17: Millions | K17: USD | L17: 35783 | M17: {=_xlfn.IFS( Movie_financials[[#This Row],[revenue]]<500,"Average", Movie_financials[[#This Row],[revenue]]<=1000,"Hit", TRUE,"Blockbuster")} -> Blockbuster | N17: {=_xlfn.IFS(Movie_financials[[#This Row],[imdb_rating]]<7,"Average",Movie_financials[[#This Row],[imdb_rating]]<=8.5,"Good",TRUE,"Excellent")} -> Good | O17: {=_xlfn.IFS(Movie_financials[[#This Row],[budget]]<50,"Low budget",Movie_financials[[#This Row],[budget]]<=150,"Medium budget",TRUE,"High budget")} -> High budget
A18: 118 | B18: It's a Wonderful Life | C18: Hollywood | D18: 1946 | E18: 8.6 | F18: Liberty Films | G18: 5 | H18: 3 | I18: 3.3 | J18: Millions | K18: USD | L18: 17156 | M18: {=_xlfn.IFS( Movie_financials[[#This Row],[revenue]]<500,"Average", Movie_financials[[#This Row],[revenue]]<=1000,"Hit", TRUE,"Blockbuster")} -> Average | N18: {=_xlfn.IFS(Movie_financials[[#This Row],[imdb_rating]]<7,"Average",Movie_financials[[#This Row],[imdb_rating]]<=8.5,"Good",TRUE,"Excellent")} -> Excellent | O18: {=_xlfn.IFS(Movie_financials[[#This Row],[budget]]<50,"Low budget",Movie_financials[[#This Row],[budget]]<=150,"Medium budget",TRUE,"High budget")} -> Low budget
A19: 119 | B19: Avatar | C19: Hollywood | D19: 2009 | E19: 7.8 | F19: 20th Century Fox | G19: 5 | H19: 237 | I19: 2847 | J19: Millions | K19: USD | L19: 40165 | M19: {=_xlfn.IFS( Movie_financials[[#This Row],[revenue]]<500,"Average", Movie_financials[[#This Row],[revenue]]<=1000,"Hit", TRUE,"Blockbuster")} -> Blockbuster | N19: {=_xlfn.IFS(Movie_financials[[#This Row],[imdb_rating]]<7,"Average",Movie_financials[[#This Row],[imdb_rating]]<=8.5,"Good",TRUE,"Excellent")} -> Good | O19: {=_xlfn.IFS(Movie_financials[[#This Row],[budget]]<50,"Low budget",Movie_financials[[#This Row],[budget]]<=150,"Medium budget",TRUE,"High budget")} -> High budget
A20: 120 | B20: The Godfather | C20: Hollywood | D20: 1972 | E20: 9.2 | F20: Paramount Pictures | G20: 5 | H20: 7 | I20: 291 | J20: Millions | K20: USD | L20: 26382 | M20: {=_xlfn.IFS( Movie_financials[[#This Row],[revenue]]<500,"Average", Movie_financials[[#This Row],[revenue]]<=1000,"Hit", TRUE,"Blockbuster")} -> Average | N20: {=_xlfn.IFS(Movie_financials[[#This Row],[imdb_rating]]<7,"Average",Movie_financials[[#This Row],[imdb_rating]]<=8.5,"Good",TRUE,"Excellent")} -> Excellent | O20: {=_xlfn.IFS(Movie_financials[[#This Row],[budget]]<50,"Low budget",Movie_financials[[#This Row],[budget]]<=150,"Medium budget",TRUE,"High budget")} -> Low budget
A21: 121 | B21: The Dark Knight | C21: Hollywood | D21: 2008 | E21: 9 | F21: Syncopy | G21: 5 | H21: 185 | I21: 1006 | J21: Millions | K21: USD | L21: 39647 | M21: {=_xlfn.IFS( Movie_financials[[#This Row],[revenue]]<500,"Average", Movie_financials[[#This Row],[revenue]]<=1000,"Hit", TRUE,"Blockbuster")} -> Blockbuster | N21: {=_xlfn.IFS(Movie_financials[[#This Row],[imdb_rating]]<7,"Average",Movie_financials[[#This Row],[imdb_rating]]<=8.5,"Good",TRUE,"Excellent")} -> Excellent | O21: {=_xlfn.IFS(Movie_financials[[#This Row],[budget]]<50,"Low budget",Movie_financials[[#This Row],[budget]]<=150,"Medium budget",TRUE,"High budget")} -> High budget
A22: 122 | B22: Schindler's List | C22: Hollywood | D22: 1993 | E22: 9 | F22: Universal Pictures | G22: 5 | H22: 22 | I22: 322.2 | J22: Millions | K22: USD | L22: 34004 | M22: {=_xlfn.IFS( Movie_financials[[#This Row],[revenue]]<500,"Average", Movie_financials[[#This Row],[revenue]]<=1000,"Hit", TRUE,"Blockbuster")} -> Average | N22: {=_xlfn.IFS(Movie_financials[[#This Row],[imdb_rating]]<7,"Average",Movie_financials[[#This Row],[imdb_rating]]<=8.5,"Good",TRUE,"Excellent")} -> Excellent | O22: {=_xlfn.IFS(Movie_financials[[#This Row],[budget]]<50,"Low budget",Movie_financials[[#This Row],[budget]]<=150,"Medium budget",TRUE,"High budget")} -> Low budget
A23: 123 | B23: Jurassic Park | C23: Hollywood | D23: 1993 | E23: 8.2 | F23: Universal Pictures | G23: 5 | H23: 63 | I23: 1046 | J23: Millions | K23: USD | L23: 34131 | M23: {=_xlfn.IFS( Movie_financials[[#This Row],[revenue]]<500,"Average", Movie_financials[[#This Row],[revenue]]<=1000,"Hit", TRUE,"Blockbuster")} -> Blockbuster | N23: {=_xlfn.IFS(Movie_financials[[#This Row],[imdb_rating]]<7,"Average",Movie_financials[[#This Row],[imdb_rating]]<=8.5,"Good",TRUE,"Excellent")} -> Good | O23: {=_xlfn.IFS(Movie_financials[[#This Row],[budget]]<50,"Low budget",Movie_financials[[#This Row],[budget]]<=150,"Medium budget",TRUE,"High budget")} -> Medium budget
A24: 124 | B24: Parasite | C24: Hollywood | D24: 2019 | E24: 8.5 | F24: Not Avialable | G24: 5 | H24: 16 | I24: 263.1 | J24: Millions | K24: USD | L24: 43615 | M24: {=_xlfn.IFS( Movie_financials[[#This Row],[revenue]]<500,"Average", Movie_financials[[#This Row],[revenue]]<=1000,"Hit", TRUE,"Blockbuster")} -> Average | N24: {=_xlfn.IFS(Movie_financials[[#This Row],[imdb_rating]]<7,"Average",Movie_financials[[#This Row],[imdb_rating]]<=8.5,"Good",TRUE,"Excellent")} -> Good | O24: {=_xlfn.IFS(Movie_financials[[#This Row],[budget]]<50,"Low budget",Movie_financials[[#This Row],[budget]]<=150,"Medium budget",TRUE,"High budget")} -> Low budget
A25: 125 | B25: Avengers: Endgame | C25: Hollywood | D25: 2019 | E25: 8.4 | F25: Marvel Studios | G25: 5 | H25: 400 | I25: 2798 | J25: Millions | K25: USD | L25: 43584 | M25: {=_xlfn.IFS( Movie_financials[[#This Row],[revenue]]<500,"Average", Movie_financials[[#This Row],[revenue]]<=1000,"Hit", TRUE,"Blockbuster")} -> Blockbuster | N25: {=_xlfn.IFS(Movie_financials[[#This Row],[imdb_rating]]<7,"Average",Movie_financials[[#This Row],[imdb_rating]]<=8.5,"Good",TRUE,"Excellent")} -> Good | O25: {=_xlfn.IFS(Movie_financials[[#This Row],[budget]]<50,"Low budget",Movie_financials[[#This Row],[budget]]<=150,"Medium budget",TRUE,"High budget")} -> High budget
A26: 126 | B26: Avengers: Infinity War | C26: Hollywood | D26: 2018 | E26: 8.4 | F26: Marvel Studios | G26: 5 | H26: 400 | I26: 2048 | J26: Millions | K26: USD | L26: 43217 | M26: {=_xlfn.IFS( Movie_financials[[#This Row],[revenue]]<500,"Average", Movie_financials[[#This Row],[revenue]]<=1000,"Hit", TRUE,"Blockbuster")} -> Blockbuster | N26: {=_xlfn.IFS(Movie_financials[[#This Row],[imdb_rating]]<7,"Average",Movie_financials[[#This Row],[imdb_rating]]<=8.5,"Good",TRUE,"Excellent")} -> Good | O26: {=_xlfn.IFS(Movie_financials[[#This Row],[budget]]<50,"Low budget",Movie_financials[[#This Row],[budget]]<=150,"Medium budget",TRUE,"High budget")} -> High budget
... A40: 140 | B40: Shershaah | C40: Bollywood | D40: 2021 | E40: 8.4 | F40: Dharma Productions | G40: 1 | H40: 500 | I40: 950 | J40: Millions | K40: INR | L40: 44420 | M40: {=_xlfn.IFS( Movie_financials[[#This Row],[revenue]]<500,"Average", Movie_financials[[#This Row],[revenue]]<=1000,"Hit", TRUE,"Blockbuster")} -> Hit | N40: {=_xlfn.IFS(Movie_financials[[#This Row],[imdb_rating]]<7,"Average",Movie_financials[[#This Row],[imdb_rating]]<=8.5,"Good",TRUE,"Excellent")} -> Good | O40: {=_xlfn.IFS(Movie_financials[[#This Row],[budget]]<50,"Low budget",Movie_financials[[#This Row],[budget]]<=150,"Medium budget",TRUE,"High budget")} -> High budget

Sheet DAY 4
A2: Text functions in Excel
A4: Studio_number | B4: Extracted_studio_number | C4: Trim checking | D4: value checking
A5: Studio- 101 | B5: =VALUE(TRIM(RIGHT(Table9[[#This Row],[Studio_number]],LEN(Table9[[#This Row],[Studio_number]])-FIND("-",Table9[[#This Row],[Studio_number]],6)))) -> 101 | C5: =LEN(Table9[[#This Row],[Extracted_studio_number]]) -> 3 | D5: =ISNUMBER(Table9[[#This Row],[Extracted_studio_number]]) -> TRUE
A6: Studio- 102 | B6: =VALUE(TRIM(RIGHT(Table9[[#This Row],[Studio_number]],LEN(Table9[[#This Row],[Studio_number]])-FIND("-",Table9[[#This Row],[Studio_number]],6)))) -> 102 | C6: =LEN(Table9[[#This Row],[Extracted_studio_number]]) -> 3 | D6: =ISNUMBER(Table9[[#This Row],[Extracted_studio_number]]) -> TRUE
A7: Studio-103 | B7: =VALUE(TRIM(RIGHT(Table9[[#This Row],[Studio_number]],LEN(Table9[[#This Row],[Studio_number]])-FIND("-",Table9[[#This Row],[Studio_number]],6)))) -> 103 | C7: =LEN(Table9[[#This Row],[Extracted_studio_number]]) -> 3 | D7: =ISNUMBER(Table9[[#This Row],[Extracted_studio_number]]) -> TRUE
A8: Studio-104 | B8: =VALUE(TRIM(RIGHT(Table9[[#This Row],[Studio_number]],LEN(Table9[[#This Row],[Studio_number]])-FIND("-",Table9[[#This Row],[Studio_number]],6)))) -> 104 | C8: =LEN(Table9[[#This Row],[Extracted_studio_number]]) -> 3 | D8: =ISNUMBER(Table9[[#This Row],[Extracted_studio_number]]) -> TRUE
A9: Studio-105 | B9: =VALUE(TRIM(RIGHT(Table9[[#This Row],[Studio_number]],LEN(Table9[[#This Row],[Studio_number]])-FIND("-",Table9[[#This Row],[Studio_number]],6)))) -> 105 | C9: =LEN(Table9[[#This Row],[Extracted_studio_number]]) -> 3 | D9: =ISNUMBER(Table9[[#This Row],[Extracted_studio_number]]) -> TRUE
A10: Studio-106 | B10: =VALUE(TRIM(RIGHT(Table9[[#This Row],[Studio_number]],LEN(Table9[[#This Row],[Studio_number]])-FIND("-",Table9[[#This Row],[Studio_number]],6)))) -> 106 | C10: =LEN(Table9[[#This Row],[Extracted_studio_number]]) -> 3 | D10: =ISNUMBER(Table9[[#This Row],[Extracted_studio_number]]) -> TRUE
A11: Studio-107 | B11: =VALUE(TRIM(RIGHT(Table9[[#This Row],[Studio_number]],LEN(Table9[[#This Row],[Studio_number]])-FIND("-",Table9[[#This Row],[Studio_number]],6)))) -> 107 | C11: =LEN(Table9[[#This Row],[Extracted_studio_number]]) -> 3 | D11: =ISNUMBER(Table9[[#This Row],[Extracted_studio_number]]) -> TRUE
A12: Studio-108 | B12: =VALUE(TRIM(RIGHT(Table9[[#This Row],[Studio_number]],LEN(Table9[[#This Row],[Studio_number]])-FIND("-",Table9[[#This Row],[Studio_number]],6)))) -> 108 | C12: =LEN(Table9[[#This Row],[Extracted_studio_number]]) -> 3 | D12: =ISNUMBER(Table9[[#This Row],[Extracted_studio_number]]) -> TRUE
A13: Studio-109 | B13: =VALUE(TRIM(RIGHT(Table9[[#This Row],[Studio_number]],LEN(Table9[[#This Row],[Studio_number]])-FIND("-",Table9[[#This Row],[Studio_number]],6)))) -> 109 | C13: =LEN(Table9[[#This Row],[Extracted_studio_number]]) -> 3 | D13: =ISNUMBER(Table9[[#This Row],[Extracted_studio_number]]) -> TRUE
A14: Studio-110 | B14: =VALUE(TRIM(RIGHT(Table9[[#This Row],[Studio_number]],LEN(Table9[[#This Row],[Studio_number]])-FIND("-",Table9[[#This Row],[Studio_number]],6)))) -> 110 | C14: =LEN(Table9[[#This Row],[Extracted_studio_number]]) -> 3 | D14: =ISNUMBER(Table9[[#This Row],[Extracted_studio_number]]) -> TRUE
A15: Studio-1111 | B15: =VALUE(TRIM(RIGHT(Table9[[#This Row],[Studio_number]],LEN(Table9[[#This Row],[Studio_number]])-FIND("-",Table9[[#This Row],[Studio_number]],6)))) -> 1111 | C15: =LEN(Table9[[#This Row],[Extracted_studio_number]]) -> 4 | D15: =ISNUMBER(Table9[[#This Row],[Extracted_studio_number]]) -> TRUE
A16: Studio-1112 | B16: =VALUE(TRIM(RIGHT(Table9[[#This Row],[Studio_number]],LEN(Table9[[#This Row],[Studio_number]])-FIND("-",Table9[[#This Row],[Studio_number]],6)))) -> 1112 | C16: =LEN(Table9[[#This Row],[Extracted_studio_number]]) -> 4 | D16: =ISNUMBER(Table9[[#This Row],[Extracted_studio_number]]) -> TRUE
... A22: Studio-118 | B22: =VALUE(TRIM(RIGHT(Table9[[#This Row],[Studio_number]],LEN(Table9[[#This Row],[Studio_number]])-FIND("-",Table9[[#This Row],[Studio_number]],6)))) -> 118 | C22: =LEN(Table9[[#This Row],[Extracted_studio_number]]) -> 3 | D22: =ISNUMBER(Table9[[#This Row],[Extracted_studio_number]]) -> TRUE

Sheet DAY 5
A1: Movie_id | B1: Title | C1: industry | D1: release_year | E1: imdb_rating | F1: studio | G1: language_id | H1: budget | I1: revenue | J1: unit | K1: currency | L1: release_date | M1: Movie_performance | N1: Rating_category | O1: Budget_category | P1: Movie_age | Q1: Movie_age(years) | R1: Movie_era | S1: profit_category | T1: Imdb_grade | U1: revenue_category | V1: Status
A2: 101 | B2: K.G.F: Chapter 2 | C2: Bollywood | D2: 2022 | E2: 8.4 | F2: Hombale Films | G2: 3 | H2: 1 | I2: 12.5 | J2: Billions | K2: INR | L2: 44665 | M2: {=_xlfn.IFS( Movie_financials__with_release_date[[#This Row],[revenue]]<500,"Average", Movie_financials__with_release_date[[#This Row],[revenue]]<=1000,"Hit", TRUE,"Blockbuster")} -> Average | N2: {=_xlfn.IFS(Movie_financials__with_release_date[[#This Row],[imdb_rating]]<7,"Average",Movie_financials__with_release_date[[#This Row],[imdb_rating]]<=8.5,"Good",TRUE,"Excellent")} -> Good | O2: {=_xlfn.IFS(Movie_financials__with_release_date[[#This Row],[budget]]<50,"Low budget",Movie_financials__with_release_date[[#This Row],[budget]]<=150,"Medium budget",TRUE,"High budget")} -> Low budget | P2: =DATEDIF(Movie_financials__with_release_date[[#This Row],[release_date]],TODAY(),"Y")& "years"& DATEDIF(Movie_financials__with_release_date[[#This Row],[release_date]],TODAY(),"YM")& "months" -> 4years3months | Q2: =DATEDIF(Movie_financials__with_release_date[[#This Row],[release_date]],TODAY(),"Y") -> 4 | R2: {=_xlfn.IFS(Movie_financials__with_release_date[[#This Row],[Movie_age(years)]]<5,"New Release",Movie_financials__with_release_date[[#This Row],[Movie_age(years)]]<=15,"Modern Classic", TRUE,"Classic" )} -> New Release | S2: {=_xlfn.IFS(Movie_financials__with_release_date[[#This Row],[revenue]]>Movie_financials__with_release_date[[#This Row],[budget]]*3,"Highly Profitable", Movie_financials__with_release_date[[#This Row],[revenue]]>Movie_financials__with_release_date[[#This Row],[budget]],"Profitable", TRUE,"Low Profit")} -> Highly Profitable | T2: {=_xlfn.IFS(Movie_financials__with_release_date[[#This Row],[imdb_rating]]>=9,"A+", Movie_financials__with_release_date[[#This Row],[imdb_rating]]>=8,"A", Movie_financials__with_release_date[[#This Row],[imdb_rating]]>=7,"B", TRUE,"C")} -> A | U2: {=_xlfn.IFS(Movie_financials__with_release_date[[#This Row],[revenue]]>=2000,"Mega Hit", Movie_financials__with_release_date[[#This Row],[revenue]]>=1000,"Super Hit", Movie_financials__with_release_date[[#This Row],[revenue]]>=500,"Hit", TRUE,"Average")} -> Average | V2: =IF(AND(Movie_financials__with_release_date[[#This Row],[budget]]>=200,Movie_financials__with_release_date[[#This Row],[profit_category]]="Low Profit"),"⚠ Review","OK") -> OK
A3: 102 | B3: Doctor Strange in the Multiverse of Madness | C3: Hollywood | D3: 2022 | E3: 7 | F3: Marvel Studios | G3: 5 | H3: 200 | I3: 954.8 | J3: Millions | K3: USD | L3: 44687 | M3: {=_xlfn.IFS( Movie_financials__with_release_date[[#This Row],[revenue]]<500,"Average", Movie_financials__with_release_date[[#This Row],[revenue]]<=1000,"Hit", TRUE,"Blockbuster")} -> Hit | N3: {=_xlfn.IFS(Movie_financials__with_release_date[[#This Row],[imdb_rating]]<7,"Average",Movie_financials__with_release_date[[#This Row],[imdb_rating]]<=8.5,"Good",TRUE,"Excellent")} -> Good | O3: {=_xlfn.IFS(Movie_financials__with_release_date[[#This Row],[budget]]<50,"Low budget",Movie_financials__with_release_date[[#This Row],[budget]]<=150,"Medium budget",TRUE,"High budget")} -> High budget | P3: =DATEDIF(Movie_financials__with_release_date[[#This Row],[release_date]],TODAY(),"Y")& "years"& DATEDIF(Movie_financials__with_release_date[[#This Row],[release_date]],TODAY(),"YM")& "months" -> 4years2months | Q3: =DATEDIF(Movie_financials__with_release_date[[#This Row],[release_date]],TODAY(),"Y") -> 4 | R3: {=_xlfn.IFS(Movie_financials__with_release_date[[#This Row],[Movie_age(years)]]<5,"New Release",Movie_financials__with_release_date[[#This Row],[Movie_age(years)]]<=15,"Modern Classic", TRUE,"Classic" )} -> New Release | S3: {=_xlfn.IFS(Movie_financials__with_release_date[[#This Row],[revenue]]>Movie_financials__with_release_date[[#This Row],[budget]]*3,"Highly Profitable", Movie_financials__with_release_date[[#This Row],[revenue]]>Movie_financials__with_release_date[[#This Row],[budget]],"Profitable", TRUE,"Low Profit")} -> Highly Profitable | T3: {=_xlfn.IFS(Movie_financials__with_release_date[[#This Row],[imdb_rating]]>=9,"A+", Movie_financials__with_release_date[[#This Row],[imdb_rating]]>=8,"A", Movie_financials__with_release_date[[#This Row],[imdb_rating]]>=7,"B", TRUE,"C")} -> B | U3: {=_xlfn.IFS(Movie_financials__with_release_date[[#This Row],[revenue]]>=2000,"Mega Hit", Movie_financials__with_release_date[[#This Row],[revenue]]>=1000,"Super Hit", Movie_financials__with_release_date[[#This Row],[revenue]]>=500,"Hit", TRUE,"Average")} -> Hit | V3: =IF(AND(Movie_financials__with_release_date[[#This Row],[budget]]>=200,Movie_financials__with_release_date[[#This Row],[profit_category]]="Low Profit"),"⚠ Review","OK") -> OK
A4: 103 | B4: Thor: The Dark World | C4: Hollywood | D4: 2013 | E4: 6.8 | F4: Marvel Studios | G4: 5 | H4: 165 | I4: 644.8 | J4: Millions | K4: USD | L4: 41586 | M4: {=_xlfn.IFS( Movie_financials__with_release_date[[#This Row],[revenue]]<500,"Average", Movie_financials__with_release_date[[#This Row],[revenue]]<=1000,"Hit", TRUE,"Blockbuster")} -> Hit | N4: {=_xlfn.IFS(Movie_financials__with_release_date[[#This Row],[imdb_rating]]<7,"Average",Movie_financials__with_release_date[[#This Row],[imdb_rating]]<=8.5,"Good",TRUE,"Excellent")} -> Average | O4: {=_xlfn.IFS(Movie_financials__with_release_date[[#This Row],[budget]]<50,"Low budget",Movie_financials__with_release_date[[#This Row],[budget]]<=150,"Medium budget",TRUE,"High budget")} -> High budget | P4: =DATEDIF(Movie_financials__with_release_date[[#This Row],[release_date]],TODAY(),"Y")& "years"& DATEDIF(Movie_financials__with_release_date[[#This Row],[release_date]],TODAY(),"YM")& "months" -> 12years8months | Q4: =DATEDIF(Movie_financials__with_release_date[[#This Row],[release_date]],TODAY(),"Y") -> 12 | R4: {=_xlfn.IFS(Movie_financials__with_release_date[[#This Row],[Movie_age(years)]]<5,"New Release",Movie_financials__with_release_date[[#This Row],[Movie_age(years)]]<=15,"Modern Classic", TRUE,"Classic" )} -> Modern Classic | S4: {=_xlfn.IFS(Movie_financials__with_release_date[[#This Row],[revenue]]>Movie_financials__with_release_date[[#This Row],[budget]]*3,"Highly Profitable", Movie_financials__with_release_date[[#This Row],[revenue]]>Movie_financials__with_release_date[[#This Row],[budget]],"Profitable", TRUE,"Low Profit")} -> Highly Profitable | T4: {=_xlfn.IFS(Movie_financials__with_release_date[[#This Row],[imdb_rating]]>=9,"A+", Movie_financials__with_release_date[[#This Row],[imdb_rating]]>=8,"A", Movie_financials__with_release_date[[#This Row],[imdb_rating]]>=7,"B", TRUE,"C")} -> C | U4: {=_xlfn.IFS(Movie_financials__with_release_date[[#This Row],[revenue]]>=2000,"Mega Hit", Movie_financials__with_release_date[[#This Row],[revenue]]>=1000,"Super Hit", Movie_financials__with_release_date[[#This Row],[revenue]]>=500,"Hit", TRUE,"Average")} -> Hit | V4: =IF(AND(Movie_financials__with_release_date[[#This Row],[budget]]>=200,Movie_financials__with_release_date[[#This Row],[profit_category]]="Low Profit"),"⚠ Review","OK") -> OK
A5: 104 | B5: Thor: Ragnarok | C5: Hollywood | D5: 2017 | E5: 7.9 | F5: Marvel Studios | G5: 5 | H5: 180 | I5: 854 | J5: Millions | K5: USD | L5: 43042 | M5: {=_xlfn.IFS( Movie_financials__with_release_date[[#This Row],[revenue]]<500,"Average", Movie_financials__with_release_date[[#This Row],[revenue]]<=1000,"Hit", TRUE,"Blockbuster")} -> Hit | N5: {=_xlfn.IFS(Movie_financials__with_release_date[[#This Row],[imdb_rating]]<7,"Average",Movie_financials__with_release_date[[#This Row],[imdb_rating]]<=8.5,"Good",TRUE,"Excellent")} -> Good | O5: {=_xlfn.IFS(Movie_financials__with_release_date[[#This Row],[budget]]<50,"Low budget",Movie_financials__with_release_date[[#This Row],[budget]]<=150,"Medium budget",TRUE,"High budget")} -> High budget | P5: =DATEDIF(Movie_financials__with_release_date[[#This Row],[release_date]],TODAY(),"Y")& "years"& DATEDIF(Movie_financials__with_release_date[[#This Row],[release_date]],TODAY(),"YM")& "months" -> 8years8months | Q5: =DATEDIF(Movie_financials__with_release_date[[#This Row],[release_date]],TODAY(),"Y") -> 8 | R5: {=_xlfn.IFS(Movie_financials__with_release_date[[#This Row],[Movie_age(years)]]<5,"New Release",Movie_financials__with_release_date[[#This Row],[Movie_age(years)]]<=15,"Modern Classic", TRUE,"Classic" )} -> Modern Classic | S5: {=_xlfn.IFS(Movie_financials__with_release_date[[#This Row],[revenue]]>Movie_financials__with_release_date[[#This Row],[budget]]*3,"Highly Profitable", Movie_financials__with_release_date[[#This Row],[revenue]]>Movie_financials__with_release_date[[#This Row],[budget]],"Profitable", TRUE,"Low Profit")} -> Highly Profitable | T5: {=_xlfn.IFS(Movie_financials__with_release_date[[#This Row],[imdb_rating]]>=9,"A+", Movie_financials__with_release_date[[#This Row],[imdb_rating]]>=8,"A", Movie_financials__with_release_date[[#This Row],[imdb_rating]]>=7,"B", TRUE,"C")} -> B | U5: {=_xlfn.IFS(Movie_financials__with_release_date[[#This Row],[revenue]]>=2000,"Mega Hit", Movie_financials__with_release_date[[#This Row],[revenue]]>=1000,"Super Hit", Movie_financials__with_release_date[[#This Row],[revenue]]>=500,"Hit", TRUE,"Average")} -> Hit | V5: =IF(AND(Movie_financials__with_release_date[[#This Row],[budget]]>=200,Movie_financials__with_release_date[[#This Row],[profit_category]]="Low Profit"),"⚠ Review","OK") -> OK
A6: 105 | B6: Thor: Love and Thunder | C6: Hollywood | D6: 2022 | E6: 6.8 | F6: Marvel Studios | G6: 5 | H6: 250 | I6: 670 | J6: Millions | K6: USD | L6: 44750 | M6: {=_xlfn.IFS( Movie_financials__with_release_date[[#This Row],[revenue]]<500,"Average", Movie_financials__with_release_date[[#This Row],[revenue]]<=1000,"Hit", TRUE,"Blockbuster")} -> Hit | N6: {=_xlfn.IFS(Movie_financials__with_release_date[[#This Row],[imdb_rating]]<7,"Average",Movie_financials__with_release_date[[#This Row],[imdb_rating]]<=8.5,"Good",TRUE,"Excellent")} -> Average | O6: {=_xlfn.IFS(Movie_financials__with_release_date[[#This Row],[budget]]<50,"Low budget",Movie_financials__with_release_date[[#This Row],[budget]]<=150,"Medium budget",TRUE,"High budget")} -> High budget | P6: =DATEDIF(Movie_financials__with_release_date[[#This Row],[release_date]],TODAY(),"Y")& "years"& DATEDIF(Movie_financials__with_release_date[[#This Row],[release_date]],TODAY(),"YM")& "months" -> 4years0months | Q6: =DATEDIF(Movie_financials__with_release_date[[#This Row],[release_date]],TODAY(),"Y") -> 4 | R6: {=_xlfn.IFS(Movie_financials__with_release_date[[#This Row],[Movie_age(years)]]<5,"New Release",Movie_financials__with_release_date[[#This Row],[Movie_age(years)]]<=15,"Modern Classic", TRUE,"Classic" )} -> New Release | S6: {=_xlfn.IFS(Movie_financials__with_release_date[[#This Row],[revenue]]>Movie_financials__with_release_date[[#This Row],[budget]]*3,"Highly Profitable", Movie_financials__with_release_date[[#This Row],[revenue]]>Movie_financials__with_release_date[[#This Row],[budget]],"Profitable", TRUE,"Low Profit")} -> Profitable | T6: {=_xlfn.IFS(Movie_financials__with_release_date[[#This Row],[imdb_rating]]>=9,"A+", Movie_financials__with_release_date[[#This Row],[imdb_rating]]>=8,"A", Movie_financials__with_release_date[[#This Row],[imdb_rating]]>=7,"B", TRUE,"C")} -> C | U6: {=_xlfn.IFS(Movie_financials__with_release_date[[#This Row],[revenue]]>=2000,"Mega Hit", Movie_financials__with_release_date[[#This Row],[revenue]]>=1000,"Super Hit", Movie_financials__with_release_date[[#This Row],[revenue]]>=500,"Hit", TRUE,"Average")} -> Hit | V6: =IF(AND(Movie_financials__with_release_date[[#This Row],[budget]]>=200,Movie_financials__with_release_date[[#This Row],[profit_category]]="Low Profit"),"⚠ Review","OK") -> OK
A7: 106 | B7: Sholay | C7: Bollywood | D7: 1975 | E7: 8.1 | F7: United Producers | G7: 1 | L7: 27621 | M7: {=_xlfn.IFS( Movie_financials__with_release_date[[#This Row],[revenue]]<500,"Average", Movie_financials__with_release_date[[#This Row],[revenue]]<=1000,"Hit", TRUE,"Blockbuster")} -> Average | N7: {=_xlfn.IFS(Movie_financials__with_release_date[[#This Row],[imdb_rating]]<7,"Average",Movie_financials__with_release_date[[#This Row],[imdb_rating]]<=8.5,"Good",TRUE,"Excellent")} -> Good | O7: {=_xlfn.IFS(Movie_financials__with_release_date[[#This Row],[budget]]<50,"Low budget",Movie_financials__with_release_date[[#This Row],[budget]]<=150,"Medium budget",TRUE,"High budget")} -> Low budget | P7: =DATEDIF(Movie_financials__with_release_date[[#This Row],[release_date]],TODAY(),"Y")& "years"& DATEDIF(Movie_financials__with_release_date[[#This Row],[release_date]],TODAY(),"YM")& "months" -> 50years11months | Q7: =DATEDIF(Movie_financials__with_release_date[[#This Row],[release_date]],TODAY(),"Y") -> 50 | R7: {=_xlfn.IFS(Movie_financials__with_release_date[[#This Row],[Movie_age(years)]]<5,"New Release",Movie_financials__with_release_date[[#This Row],[Movie_age(years)]]<=15,"Modern Classic", TRUE,"Classic" )} -> Classic | S7: {=_xlfn.IFS(Movie_financials__with_release_date[[#This Row],[revenue]]>Movie_financials__with_release_date[[#This Row],[budget]]*3,"Highly Profitable", Movie_financials__with_release_date[[#This Row],[revenue]]>Movie_financials__with_release_date[[#This Row],[budget]],"Profitable", TRUE,"Low Profit")} -> Low Profit | T7: {=_xlfn.IFS(Movie_financials__with_release_date[[#This Row],[imdb_rating]]>=9,"A+", Movie_financials__with_release_date[[#This Row],[imdb_rating]]>=8,"A", Movie_financials__with_release_date[[#This Row],[imdb_rating]]>=7,"B", TRUE,"C")} -> A | U7: {=_xlfn.IFS(Movie_financials__with_release_date[[#This Row],[revenue]]>=2000,"Mega Hit", Movie_financials__with_release_date[[#This Row],[revenue]]>=1000,"Super Hit", Movie_financials__with_release_date[[#This Row],[revenue]]>=500,"Hit", TRUE,"Average")} -> Average | V7: =IF(AND(Movie_financials__with_release_date[[#This Row],[budget]]>=200,Movie_financials__with_release_date[[#This Row],[profit_category]]="Low Profit"),"⚠ Review","OK") -> OK
A8: 107 | B8: Dilwale Dulhania Le Jayenge | C8: Bollywood | D8: 1995 | E8: 8 | F8: Yash Raj Films | G8: 1 | H8: 400 | I8: 2000 | J8: Millions | K8: INR | L8: 34992 | M8: {=_xlfn.IFS( Movie_financials__with_release_date[[#This Row],[revenue]]<500,"Average", Movie_financials__with_release_date[[#This Row],[revenue]]<=1000,"Hit", TRUE,"Blockbuster")} -> Blockbuster | N8: {=_xlfn.IFS(Movie_financials__with_release_date[[#This Row],[imdb_rating]]<7,"Average",Movie_financials__with_release_date[[#This Row],[imdb_rating]]<=8.5,"Good",TRUE,"Excellent")} -> Good | O8: {=_xlfn.IFS(Movie_financials__with_release_date[[#This Row],[budget]]<50,"Low budget",Movie_financials__with_release_date[[#This Row],[budget]]<=150,"Medium budget",TRUE,"High budget")} -> High budget | P8: =DATEDIF(Movie_financials__with_release_date[[#This Row],[release_date]],TODAY(),"Y")& "years"& DATEDIF(Movie_financials__with_release_date[[#This Row],[release_date]],TODAY(),"YM")& "months" -> 30years9months | Q8: =DATEDIF(Movie_financials__with_release_date[[#This Row],[release_date]],TODAY(),"Y") -> 30 | R8: {=_xlfn.IFS(Movie_financials__with_release_date[[#This Row],[Movie_age(years)]]<5,"New Release",Movie_financials__with_release_date[[#This Row],[Movie_age(years)]]<=15,"Modern Classic", TRUE,"Classic" )} -> Classic | S8: {=_xlfn.IFS(Movie_financials__with_release_date[[#This Row],[revenue]]>Movie_financials__with_release_date[[#This Row],[budget]]*3,"Highly Profitable", Movie_financials__with_release_date[[#This Row],[revenue]]>Movie_financials__with_release_date[[#This Row],[budget]],"Profitable", TRUE,"Low Profit")} -> Highly Profitable | T8: {=_xlfn.IFS(Movie_financials__with_release_date[[#This Row],[imdb_rating]]>=9,"A+", Movie_financials__with_release_date[[#This Row],[imdb_rating]]>=8,"A", Movie_financials__with_release_date[[#This Row],[imdb_rating]]>=7,"B", TRUE,"C")} -> A | U8: {=_xlfn.IFS(Movie_financials__with_release_date[[#This Row],[revenue]]>=2000,"Mega Hit", Movie_financials__with_release_date[[#This Row],[revenue]]>=1000,"Super Hit", Movie_financials__with_release_date[[#This Row],[revenue]]>=500,"Hit", TRUE,"Average")} -> Mega Hit | V8: =IF(AND(Movie_financials__with_release_date[[#This Row],[budget]]>=200,Movie_financials__with_release_date[[#This Row],[profit_category]]="Low Profit"),"⚠ Review","OK") -> OK
A9: 108 | B9: 3 Idiots | C9: Bollywood | D9: 2009 | E9: 8.4 | F9: Vinod Chopra Films | G9: 1 | H9: 550 | I9: 4000 | J9: Millions | K9: INR | L9: 40172 | M9: {=_xlfn.IFS( Movie_financials__with_release_date[[#This Row],[revenue]]<500,"Average", Movie_financials__with_release_date[[#This Row],[revenue]]<=1000,"Hit", TRUE,"Blockbuster")} -> Blockbuster | N9: {=_xlfn.IFS(Movie_financials__with_release_date[[#This Row],[imdb_rating]]<7,"Average",Movie_financials__with_release_date[[#This Row],[imdb_rating]]<=8.5,"Good",TRUE,"Excellent")} -> Good | O9: {=_xlfn.IFS(Movie_financials__with_release_date[[#This Row],[budget]]<50,"Low budget",Movie_financials__with_release_date[[#This Row],[budget]]<=150,"Medium budget",TRUE,"High budget")} -> High budget | P9: =DATEDIF(Movie_financials__with_release_date[[#This Row],[release_date]],TODAY(),"Y")& "years"& DATEDIF(Movie_financials__with_release_date[[#This Row],[release_date]],TODAY(),"YM")& "months" -> 16years6months | Q9: =DATEDIF(Movie_financials__with_release_date[[#This Row],[release_date]],TODAY(),"Y") -> 16 | R9: {=_xlfn.IFS(Movie_financials__with_release_date[[#This Row],[Movie_age(years)]]<5,"New Release",Movie_financials__with_release_date[[#This Row],[Movie_age(years)]]<=15,"Modern Classic", TRUE,"Classic" )} -> Classic | S9: {=_xlfn.IFS(Movie_financials__with_release_date[[#This Row],[revenue]]>Movie_financials__with_release_date[[#This Row],[budget]]*3,"Highly Profitable", Movie_financials__with_release_date[[#This Row],[revenue]]>Movie_financials__with_release_date[[#This Row],[budget]],"Profitable", TRUE,"Low Profit")} -> Highly Profitable | T9: {=_xlfn.IFS(Movie_financials__with_release_date[[#This Row],[imdb_rating]]>=9,"A+", Movie_financials__with_release_date[[#This Row],[imdb_rating]]>=8,"A", Movie_financials__with_release_date[[#This Row],[imdb_rating]]>=7,"B", TRUE,"C")} -> A | U9: {=_xlfn.IFS(Movie_financials__with_release_date[[#This Row],[revenue]]>=2000,"Mega Hit", Movie_financials__with_release_date[[#This Row],[revenue]]>=1000,"Super Hit", Movie_financials__with_release_date[[#This Row],[revenue]]>=500,"Hit", TRUE,"Average")} -> Mega Hit | V9: =IF(AND(Movie_financials__with_release_date[[#This Row],[budget]]>=200,Movie_financials__with_release_date[[#This Row],[profit_category]]="Low Profit"),"⚠ Review","OK") -> OK
A10: 109 | B10: Kabhi Khushi Kabhie Gham | C10: Bollywood | D10: 2001 | E10: 7.4 | F10: Dharma Productions | G10: 1 | H10: 390 | I10: 1360 | J10: Millions | K10: INR | L10: 37239 | M10: {=_xlfn.IFS( Movie_financials__with_release_date[[#This Row],[revenue]]<500,"Average", Movie_financials__with_release_date[[#This Row],[revenue]]<=1000,"Hit", TRUE,"Blockbuster")} -> Blockbuster | N10: {=_xlfn.IFS(Movie_financials__with_release_date[[#This Row],[imdb_rating]]<7,"Average",Movie_financials__with_release_date[[#This Row],[imdb_rating]]<=8.5,"Good",TRUE,"Excellent")} -> Good | O10: {=_xlfn.IFS(Movie_financials__with_release_date[[#This Row],[budget]]<50,"Low budget",Movie_financials__with_release_date[[#This Row],[budget]]<=150,"Medium budget",TRUE,"High budget")} -> High budget | P10: =DATEDIF(Movie_financials__with_release_date[[#This Row],[release_date]],TODAY(),"Y")& "years"& DATEDIF(Movie_financials__with_release_date[[#This Row],[release_date]],TODAY(),"YM")& "months" -> 24years7months | Q10: =DATEDIF(Movie_financials__with_release_date[[#This Row],[release_date]],TODAY(),"Y") -> 24 | R10: {=_xlfn.IFS(Movie_financials__with_release_date[[#This Row],[Movie_age(years)]]<5,"New Release",Movie_financials__with_release_date[[#This Row],[Movie_age(years)]]<=15,"Modern Classic", TRUE,"Classic" )} -> Classic | S10: {=_xlfn.IFS(Movie_financials__with_release_date[[#This Row],[revenue]]>Movie_financials__with_release_date[[#This Row],[budget]]*3,"Highly Profitable", Movie_financials__with_release_date[[#This Row],[revenue]]>Movie_financials__with_release_date[[#This Row],[budget]],"Profitable", TRUE,"Low Profit")} -> Highly Profitable | T10: {=_xlfn.IFS(Movie_financials__with_release_date[[#This Row],[imdb_rating]]>=9,"A+", Movie_financials__with_release_date[[#This Row],[imdb_rating]]>=8,"A", Movie_financials__with_release_date[[#This Row],[imdb_rating]]>=7,"B", TRUE,"C")} -> B | U10: {=_xlfn.IFS(Movie_financials__with_release_date[[#This Row],[revenue]]>=2000,"Mega Hit", Movie_financials__with_release_date[[#This Row],[revenue]]>=1000,"Super Hit", Movie_financials__with_release_date[[#This Row],[revenue]]>=500,"Hit", TRUE,"Average")} -> Super Hit | V10: =IF(AND(Movie_financials__with_release_date[[#This Row],[budget]]>=200,Movie_financials__with_release_date[[#This Row],[profit_category]]="Low Profit"),"⚠ Review","OK") -> OK
A11: 110 | B11: Bajirao Mastani | C11: Bollywood | D11: 2015 | E11: 7.2 | F11: Not Avialable | G11: 1 | H11: 1 | I11: 3.5 | J11: Billions | K11: INR | L11: 42356 | M11: {=_xlfn.IFS( Movie_financials__with_release_date[[#This Row],[revenue]]<500,"Average", Movie_financials__with_release_date[[#This Row],[revenue]]<=1000,"Hit", TRUE,"Blockbuster")} -> Average | N11: {=_xlfn.IFS(Movie_financials__with_release_date[[#This Row],[imdb_rating]]<7,"Average",Movie_financials__with_release_date[[#This Row],[imdb_rating]]<=8.5,"Good",TRUE,"Excellent")} -> Good | O11: {=_xlfn.IFS(Movie_financials__with_release_date[[#This Row],[budget]]<50,"Low budget",Movie_financials__with_release_date[[#This Row],[budget]]<=150,"Medium budget",TRUE,"High budget")} -> Low budget | P11: =DATEDIF(Movie_financials__with_release_date[[#This Row],[release_date]],TODAY(),"Y")& "years"& DATEDIF(Movie_financials__with_release_date[[#This Row],[release_date]],TODAY(),"YM")& "months" -> 10years7months | Q11: =DATEDIF(Movie_financials__with_release_date[[#This Row],[release_date]],TODAY(),"Y") -> 10 | R11: {=_xlfn.IFS(Movie_financials__with_release_date[[#This Row],[Movie_age(years)]]<5,"New Release",Movie_financials__with_release_date[[#This Row],[Movie_age(years)]]<=15,"Modern Classic", TRUE,"Classic" )} -> Modern Classic | S11: {=_xlfn.IFS(Movie_financials__with_release_date[[#This Row],[revenue]]>Movie_financials__with_release_date[[#This Row],[budget]]*3,"Highly Profitable", Movie_financials__with_release_date[[#This Row],[revenue]]>Movie_financials__with_release_date[[#This Row],[budget]],"Profitable", TRUE,"Low Profit")} -> Highly Profitable | T11: {=_xlfn.IFS(Movie_financials__with_release_date[[#This Row],[imdb_rating]]>=9,"A+", Movie_financials__with_release_date[[#This Row],[imdb_rating]]>=8,"A", Movie_financials__with_release_date[[#This Row],[imdb_rating]]>=7,"B", TRUE,"C")} -> B | U11: {=_xlfn.IFS(Movie_financials__with_release_date[[#This Row],[revenue]]>=2000,"Mega Hit", Movie_financials__with_release_date[[#This Row],[revenue]]>=1000,"Super Hit", Movie_financials__with_release_date[[#This Row],[revenue]]>=500,"Hit", TRUE,"Average")} -> Average | V11: =IF(AND(Movie_financials__with_release_date[[#This Row],[budget]]>=200,Movie_financials__with_release_date[[#This Row],[profit_category]]="Low Profit"),"⚠ Review","OK") -> OK
A12: 111 | B12: The Shawshank Redemption | C12: Hollywood | D12: 1994 | E12: 9.3 | F12: Castle Rock Entertainment | G12: 5 | H12: 25 | I12: 73.3 | J12: Millions | K12: USD | L12: 34600 | M12: {=_xlfn.IFS( Movie_financials__with_release_date[[#This Row],[revenue]]<500,"Average", Movie_financials__with_release_date[[#This Row],[revenue]]<=1000,"Hit", TRUE,"Blockbuster")} -> Average | N12: {=_xlfn.IFS(Movie_financials__with_release_date[[#This Row],[imdb_rating]]<7,"Average",Movie_financials__with_release_date[[#This Row],[imdb_rating]]<=8.5,"Good",TRUE,"Excellent")} -> Excellent | O12: {=_xlfn.IFS(Movie_financials__with_release_date[[#This Row],[budget]]<50,"Low budget",Movie_financials__with_release_date[[#This Row],[budget]]<=150,"Medium budget",TRUE,"High budget")} -> Low budget | P12: =DATEDIF(Movie_financials__with_release_date[[#This Row],[release_date]],TODAY(),"Y")& "years"& DATEDIF(Movie_financials__with_release_date[[#This Row],[release_date]],TODAY(),"YM")& "months" -> 31years9months | Q12: =DATEDIF(Movie_financials__with_release_date[[#This Row],[release_date]],TODAY(),"Y") -> 31 | R12: {=_xlfn.IFS(Movie_financials__with_release_date[[#This Row],[Movie_age(years)]]<5,"New Release",Movie_financials__with_release_date[[#This Row],[Movie_age(years)]]<=15,"Modern Classic", TRUE,"Classic" )} -> Classic | S12: {=_xlfn.IFS(Movie_financials__with_release_date[[#This Row],[revenue]]>Movie_financials__with_release_date[[#This Row],[budget]]*3,"Highly Profitable", Movie_financials__with_release_date[[#This Row],[revenue]]>Movie_financials__with_release_date[[#This Row],[budget]],"Profitable", TRUE,"Low Profit")} -> Profitable | T12: {=_xlfn.IFS(Movie_financials__with_release_date[[#This Row],[imdb_rating]]>=9,"A+", Movie_financials__with_release_date[[#This Row],[imdb_rating]]>=8,"A", Movie_financials__with_release_date[[#This Row],[imdb_rating]]>=7,"B", TRUE,"C")} -> A+ | U12: {=_xlfn.IFS(Movie_financials__with_release_date[[#This Row],[revenue]]>=2000,"Mega Hit", Movie_financials__with_release_date[[#This Row],[revenue]]>=1000,"Super Hit", Movie_financials__with_release_date[[#This Row],[revenue]]>=500,"Hit", TRUE,"Average")} -> Average | V12: =IF(AND(Movie_financials__with_release_date[[#This Row],[budget]]>=200,Movie_financials__with_release_date[[#This Row],[profit_category]]="Low Profit"),"⚠ Review","OK") -> OK
A13: 113 | B13: Interstellar | C13: Hollywood | D13: 2014 | E13: 8.6 | F13: Warner Bros. Pictures | G13: 5 | H13: 165 | I13: 701.8 | J13: Millions | K13: USD | L13: 41836 | M13: {=_xlfn.IFS( Movie_financials__with_release_date[[#This Row],[revenue]]<500,"Average", Movie_financials__with_release_date[[#This Row],[revenue]]<=1000,"Hit", TRUE,"Blockbuster")} -> Hit | N13: {=_xlfn.IFS(Movie_financials__with_release_date[[#This Row],[imdb_rating]]<7,"Average",Movie_financials__with_release_date[[#This Row],[imdb_rating]]<=8.5,"Good",TRUE,"Excellent")} -> Excellent | O13: {=_xlfn.IFS(Movie_financials__with_release_date[[#This Row],[budget]]<50,"Low budget",Movie_financials__with_release_date[[#This Row],[budget]]<=150,"Medium budget",TRUE,"High budget")} -> High budget | P13: =DATEDIF(Movie_financials__with_release_date[[#This Row],[release_date]],TODAY(),"Y")& "years"& DATEDIF(Movie_financials__with_release_date[[#This Row],[release_date]],TODAY(),"YM")& "months" -> 12years0months | Q13: =DATEDIF(Movie_financials__with_release_date[[#This Row],[release_date]],TODAY(),"Y") -> 12 | R13: {=_xlfn.IFS(Movie_financials__with_release_date[[#This Row],[Movie_age(years)]]<5,"New Release",Movie_financials__with_release_date[[#This Row],[Movie_age(years)]]<=15,"Modern Classic", TRUE,"Classic" )} -> Modern Classic | S13: {=_xlfn.IFS(Movie_financials__with_release_date[[#This Row],[revenue]]>Movie_financials__with_release_date[[#This Row],[budget]]*3,"Highly Profitable", Movie_financials__with_release_date[[#This Row],[revenue]]>Movie_financials__with_release_date[[#This Row],[budget]],"Profitable", TRUE,"Low Profit")} -> Highly Profitable | T13: {=_xlfn.IFS(Movie_financials__with_release_date[[#This Row],[imdb_rating]]>=9,"A+", Movie_financials__with_release_date[[#This Row],[imdb_rating]]>=8,"A", Movie_financials__with_release_date[[#This Row],[imdb_rating]]>=7,"B", TRUE,"C")} -> A | U13: {=_xlfn.IFS(Movie_financials__with_release_date[[#This Row],[revenue]]>=2000,"Mega Hit", Movie_financials__with_release_date[[#This Row],[revenue]]>=1000,"Super Hit", Movie_financials__with_release_date[[#This Row],[revenue]]>=500,"Hit", TRUE,"Average")} -> Hit | V13: =IF(AND(Movie_financials__with_release_date[[#This Row],[budget]]>=200,Movie_financials__with_release_date[[#This Row],[profit_category]]="Low Profit"),"⚠ Review","OK") -> OK
A14: 112 | B14: Inception | C14: Hollywood | D14: 2010 | E14: 8.8 | F14: Warner Bros. Pictures | G14: 5 | L14: 40489 | M14: {=_xlfn.IFS( Movie_financials__with_release_date[[#This Row],[revenue]]<500,"Average", Movie_financials__with_release_date[[#This Row],[revenue]]<=1000,"Hit", TRUE,"Blockbuster")} -> Average | N14: {=_xlfn.IFS(Movie_financials__with_release_date[[#This Row],[imdb_rating]]<7,"Average",Movie_financials__with_release_date[[#This Row],[imdb_rating]]<=8.5,"Good",TRUE,"Excellent")} -> Excellent | O14: {=_xlfn.IFS(Movie_financials__with_release_date[[#This Row],[budget]]<50,"Low budget",Movie_financials__with_release_date[[#This Row],[budget]]<=150,"Medium budget",TRUE,"High budget")} -> Low budget | P14: =DATEDIF(Movie_financials__with_release_date[[#This Row],[release_date]],TODAY(),"Y")& "years"& DATEDIF(Movie_financials__with_release_date[[#This Row],[release_date]],TODAY(),"YM")& "months" -> 15years8months | Q14: =DATEDIF(Movie_financials__with_release_date[[#This Row],[release_date]],TODAY(),"Y") -> 15 | R14: {=_xlfn.IFS(Movie_financials__with_release_date[[#This Row],[Movie_age(years)]]<5,"New Release",Movie_financials__with_release_date[[#This Row],[Movie_age(years)]]<=15,"Modern Classic", TRUE,"Classic" )} -> Modern Classic | S14: {=_xlfn.IFS(Movie_financials__with_release_date[[#This Row],[revenue]]>Movie_financials__with_release_date[[#This Row],[budget]]*3,"Highly Profitable", Movie_financials__with_release_date[[#This Row],[revenue]]>Movie_financials__with_release_date[[#This Row],[budget]],"Profitable", TRUE,"Low Profit")} -> Low Profit | T14: {=_xlfn.IFS(Movie_financials__with_release_date[[#This Row],[imdb_rating]]>=9,"A+", Movie_financials__with_release_date[[#This Row],[imdb_rating]]>=8,"A", Movie_financials__with_release_date[[#This Row],[imdb_rating]]>=7,"B", TRUE,"C")} -> A | U14: {=_xlfn.IFS(Movie_financials__with_release_date[[#This Row],[revenue]]>=2000,"Mega Hit", Movie_financials__with_release_date[[#This Row],[revenue]]>=1000,"Super Hit", Movie_financials__with_release_date[[#This Row],[revenue]]>=500,"Hit", TRUE,"Average")} -> Average | V14: =IF(AND(Movie_financials__with_release_date[[#This Row],[budget]]>=200,Movie_financials__with_release_date[[#This Row],[profit_category]]="Low Profit"),"⚠ Review","OK") -> OK
A15: 115 | B15: The Pursuit of Happyness | C15: Hollywood | D15: 2006 | E15: 8 | F15: Columbia Pictures | G15: 5 | H15: 55 | I15: 307.1 | J15: Millions | K15: USD | L15: 39066 | M15: {=_xlfn.IFS( Movie_financials__with_release_date[[#This Row],[revenue]]<500,"Average", Movie_financials__with_release_date[[#This Row],[revenue]]<=1000,"Hit", TRUE,"Blockbuster")} -> Average | N15: {=_xlfn.IFS(Movie_financials__with_release_date[[#This Row],[imdb_rating]]<7,"Average",Movie_financials__with_release_date[[#This Row],[imdb_rating]]<=8.5,"Good",TRUE,"Excellent")} -> Good | O15: {=_xlfn.IFS(Movie_financials__with_release_date[[#This Row],[budget]]<50,"Low budget",Movie_financials__with_release_date[[#This Row],[budget]]<=150,"Medium budget",TRUE,"High budget")} -> Medium budget | P15: =DATEDIF(Movie_financials__with_release_date[[#This Row],[release_date]],TODAY(),"Y")& "years"& DATEDIF(Movie_financials__with_release_date[[#This Row],[release_date]],TODAY(),"YM")& "months" -> 19years7months | Q15: =DATEDIF(Movie_financials__with_release_date[[#This Row],[release_date]],TODAY(),"Y") -> 19 | R15: {=_xlfn.IFS(Movie_financials__with_release_date[[#This Row],[Movie_age(years)]]<5,"New Release",Movie_financials__with_release_date[[#This Row],[Movie_age(years)]]<=15,"Modern Classic", TRUE,"Classic" )} -> Classic | S15: {=_xlfn.IFS(Movie_financials__with_release_date[[#This Row],[revenue]]>Movie_financials__with_release_date[[#This Row],[budget]]*3,"Highly Profitable", Movie_financials__with_release_date[[#This Row],[revenue]]>Movie_financials__with_release_date[[#This Row],[budget]],"Profitable", TRUE,"Low Profit")} -> Highly Profitable | T15: {=_xlfn.IFS(Movie_financials__with_release_date[[#This Row],[imdb_rating]]>=9,"A+", Movie_financials__with_release_date[[#This Row],[imdb_rating]]>=8,"A", Movie_financials__with_release_date[[#This Row],[imdb_rating]]>=7,"B", TRUE,"C")} -> A | U15: {=_xlfn.IFS(Movie_financials__with_release_date[[#This Row],[revenue]]>=2000,"Mega Hit", Movie_financials__with_release_date[[#This Row],[revenue]]>=1000,"Super Hit", Movie_financials__with_release_date[[#This Row],[revenue]]>=500,"Hit", TRUE,"Average")} -> Average | V15: =IF(AND(Movie_financials__with_release_date[[#This Row],[budget]]>=200,Movie_financials__with_release_date[[#This Row],[profit_category]]="Low Profit"),"⚠ Review","OK") -> OK
A16: 116 | B16: Gladiator | C16: Hollywood | D16: 2000 | E16: 8.5 | F16: Universal Pictures | G16: 5 | H16: 103 | I16: 460.5 | J16: Millions | K16: USD | L16: 36651 | M16: {=_xlfn.IFS( Movie_financials__with_release_date[[#This Row],[revenue]]<500,"Average", Movie_financials__with_release_date[[#This Row],[revenue]]<=1000,"Hit", TRUE,"Blockbuster")} -> Average | N16: {=_xlfn.IFS(Movie_financials__with_release_date[[#This Row],[imdb_rating]]<7,"Average",Movie_financials__with_release_date[[#This Row],[imdb_rating]]<=8.5,"Good",TRUE,"Excellent")} -> Good | O16: {=_xlfn.IFS(Movie_financials__with_release_date[[#This Row],[budget]]<50,"Low budget",Movie_financials__with_release_date[[#This Row],[budget]]<=150,"Medium budget",TRUE,"High budget")} -> Medium budget | P16: =DATEDIF(Movie_financials__with_release_date[[#This Row],[release_date]],TODAY(),"Y")& "years"& DATEDIF(Movie_financials__with_release_date[[#This Row],[release_date]],TODAY(),"YM")& "months" -> 26years2months | Q16: =DATEDIF(Movie_financials__with_release_date[[#This Row],[release_date]],TODAY(),"Y") -> 26 | R16: {=_xlfn.IFS(Movie_financials__with_release_date[[#This Row],[Movie_age(years)]]<5,"New Release",Movie_financials__with_release_date[[#This Row],[Movie_age(years)]]<=15,"Modern Classic", TRUE,"Classic" )} -> Classic | S16: {=_xlfn.IFS(Movie_financials__with_release_date[[#This Row],[revenue]]>Movie_financials__with_release_date[[#This Row],[budget]]*3,"Highly Profitable", Movie_financials__with_release_date[[#This Row],[revenue]]>Movie_financials__with_release_date[[#This Row],[budget]],"Profitable", TRUE,"Low Profit")} -> Highly Profitable | T16: {=_xlfn.IFS(Movie_financials__with_release_date[[#This Row],[imdb_rating]]>=9,"A+", Movie_financials__with_release_date[[#This Row],[imdb_rating]]>=8,"A", Movie_financials__with_release_date[[#This Row],[imdb_rating]]>=7,"B", TRUE,"C")} -> A | U16: {=_xlfn.IFS(Movie_financials__with_release_date[[#This Row],[revenue]]>=2000,"Mega Hit", Movie_financials__with_release_date[[#This Row],[revenue]]>=1000,"Super Hit", Movie_financials__with_release_date[[#This Row],[revenue]]>=500,"Hit", TRUE,"Average")} -> Average | V16: =IF(AND(Movie_financials__with_release_date[[#This Row],[budget]]>=200,Movie_financials__with_release_date[[#This Row],[profit_category]]="Low Profit"),"⚠ Review","OK") -> OK
A17: 117 | B17: Titanic | C17: Hollywood | D17: 1997 | E17: 7.9 | F17: Paramount Pictures | G17: 5 | H17: 200 | I17: 2202 | J17: Millions | K17: USD | L17: 35783 | M17: {=_xlfn.IFS( Movie_financials__with_release_date[[#This Row],[revenue]]<500,"Average", Movie_financials__with_release_date[[#This Row],[revenue]]<=1000,"Hit", TRUE,"Blockbuster")} -> Blockbuster | N17: {=_xlfn.IFS(Movie_financials__with_release_date[[#This Row],[imdb_rating]]<7,"Average",Movie_financials__with_release_date[[#This Row],[imdb_rating]]<=8.5,"Good",TRUE,"Excellent")} -> Good | O17: {=_xlfn.IFS(Movie_financials__with_release_date[[#This Row],[budget]]<50,"Low budget",Movie_financials__with_release_date[[#This Row],[budget]]<=150,"Medium budget",TRUE,"High budget")} -> High budget | P17: =DATEDIF(Movie_financials__with_release_date[[#This Row],[release_date]],TODAY(),"Y")& "years"& DATEDIF(Movie_financials__with_release_date[[#This Row],[release_date]],TODAY(),"YM")& "months" -> 28years7months | Q17: =DATEDIF(Movie_financials__with_release_date[[#This Row],[release_date]],TODAY(),"Y") -> 28 | R17: {=_xlfn.IFS(Movie_financials__with_release_date[[#This Row],[Movie_age(years)]]<5,"New Release",Movie_financials__with_release_date[[#This Row],[Movie_age(years)]]<=15,"Modern Classic", TRUE,"Classic" )} -> Classic | S17: {=_xlfn.IFS(Movie_financials__with_release_date[[#This Row],[revenue]]>Movie_financials__with_release_date[[#This Row],[budget]]*3,"Highly Profitable", Movie_financials__with_release_date[[#This Row],[revenue]]>Movie_financials__with_release_date[[#This Row],[budget]],"Profitable", TRUE,"Low Profit")} -> Highly Profitable | T17: {=_xlfn.IFS(Movie_financials__with_release_date[[#This Row],[imdb_rating]]>=9,"A+", Movie_financials__with_release_date[[#This Row],[imdb_rating]]>=8,"A", Movie_financials__with_release_date[[#This Row],[imdb_rating]]>=7,"B", TRUE,"C")} -> B | U17: {=_xlfn.IFS(Movie_financials__with_release_date[[#This Row],[revenue]]>=2000,"Mega Hit", Movie_financials__with_release_date[[#This Row],[revenue]]>=1000,"Super Hit", Movie_financials__with_release_date[[#This Row],[revenue]]>=500,"Hit", TRUE,"Average")} -> Mega Hit | V17: =IF(AND(Movie_financials__with_release_date[[#This Row],[budget]]>=200,Movie_financials__with_release_date[[#This Row],[profit_category]]="Low Profit"),"⚠ Review","OK") -> OK
A18: 118 | B18: It's a Wonderful Life | C18: Hollywood | D18: 1946 | E18: 8.6 | F18: Liberty Films | G18: 5 | H18: 3 | I18: 3.3 | J18: Millions | K18: USD | L18: 17156 | M18: {=_xlfn.IFS( Movie_financials__with_release_date[[#This Row],[revenue]]<500,"Average", Movie_financials__with_release_date[[#This Row],[revenue]]<=1000,"Hit", TRUE,"Blockbuster")} -> Average | N18: {=_xlfn.IFS(Movie_financials__with_release_date[[#This Row],[imdb_rating]]<7,"Average",Movie_financials__with_release_date[[#This Row],[imdb_rating]]<=8.5,"Good",TRUE,"Excellent")} -> Excellent | O18: {=_xlfn.IFS(Movie_financials__with_release_date[[#This Row],[budget]]<50,"Low budget",Movie_financials__with_release_date[[#This Row],[budget]]<=150,"Medium budget",TRUE,"High budget")} -> Low budget | P18: =DATEDIF(Movie_financials__with_release_date[[#This Row],[release_date]],TODAY(),"Y")& "years"& DATEDIF(Movie_financials__with_release_date[[#This Row],[release_date]],TODAY(),"YM")& "months" -> 79years7months | Q18: =DATEDIF(Movie_financials__with_release_date[[#This Row],[release_date]],TODAY(),"Y") -> 79 | R18: {=_xlfn.IFS(Movie_financials__with_release_date[[#This Row],[Movie_age(years)]]<5,"New Release",Movie_financials__with_release_date[[#This Row],[Movie_age(years)]]<=15,"Modern Classic", TRUE,"Classic" )} -> Classic | S18: {=_xlfn.IFS(Movie_financials__with_release_date[[#This Row],[revenue]]>Movie_financials__with_release_date[[#This Row],[budget]]*3,"Highly Profitable", Movie_financials__with_release_date[[#This Row],[revenue]]>Movie_financials__with_release_date[[#This Row],[budget]],"Profitable", TRUE,"Low Profit")} -> Profitable | T18: {=_xlfn.IFS(Movie_financials__with_release_date[[#This Row],[imdb_rating]]>=9,"A+", Movie_financials__with_release_date[[#This Row],[imdb_rating]]>=8,"A", Movie_financials__with_release_date[[#This Row],[imdb_rating]]>=7,"B", TRUE,"C")} -> A | U18: {=_xlfn.IFS(Movie_financials__with_release_date[[#This Row],[revenue]]>=2000,"Mega Hit", Movie_financials__with_release_date[[#This Row],[revenue]]>=1000,"Super Hit", Movie_financials__with_release_date[[#This Row],[revenue]]>=500,"Hit", TRUE,"Average")} -> Average | V18: =IF(AND(Movie_financials__with_release_date[[#This Row],[budget]]>=200,Movie_financials__with_release_date[[#This Row],[profit_category]]="Low Profit"),"⚠ Review","OK") -> OK
A19: 119 | B19: Avatar | C19: Hollywood | D19: 2009 | E19: 7.8 | F19: 20th Century Fox | G19: 5 | H19: 237 | I19: 2847 | J19: Millions | K19: USD | L19: 40165 | M19: {=_xlfn.IFS( Movie_financials__with_release_date[[#This Row],[revenue]]<500,"Average", Movie_financials__with_release_date[[#This Row],[revenue]]<=1000,"Hit", TRUE,"Blockbuster")} -> Blockbuster | N19: {=_xlfn.IFS(Movie_financials__with_release_date[[#This Row],[imdb_rating]]<7,"Average",Movie_financials__with_release_date[[#This Row],[imdb_rating]]<=8.5,"Good",TRUE,"Excellent")} -> Good | O19: {=_xlfn.IFS(Movie_financials__with_release_date[[#This Row],[budget]]<50,"Low budget",Movie_financials__with_release_date[[#This Row],[budget]]<=150,"Medium budget",TRUE,"High budget")} -> High budget | P19: =DATEDIF(Movie_financials__with_release_date[[#This Row],[release_date]],TODAY(),"Y")& "years"& DATEDIF(Movie_financials__with_release_date[[#This Row],[release_date]],TODAY(),"YM")& "months" -> 16years7months | Q19: =DATEDIF(Movie_financials__with_release_date[[#This Row],[release_date]],TODAY(),"Y") -> 16 | R19: {=_xlfn.IFS(Movie_financials__with_release_date[[#This Row],[Movie_age(years)]]<5,"New Release",Movie_financials__with_release_date[[#This Row],[Movie_age(years)]]<=15,"Modern Classic", TRUE,"Classic" )} -> Classic | S19: {=_xlfn.IFS(Movie_financials__with_release_date[[#This Row],[revenue]]>Movie_financials__with_release_date[[#This Row],[budget]]*3,"Highly Profitable", Movie_financials__with_release_date[[#This Row],[revenue]]>Movie_financials__with_release_date[[#This Row],[budget]],"Profitable", TRUE,"Low Profit")} -> Highly Profitable | T19: {=_xlfn.IFS(Movie_financials__with_release_date[[#This Row],[imdb_rating]]>=9,"A+", Movie_financials__with_release_date[[#This Row],[imdb_rating]]>=8,"A", Movie_financials__with_release_date[[#This Row],[imdb_rating]]>=7,"B", TRUE,"C")} -> B | U19: {=_xlfn.IFS(Movie_financials__with_release_date[[#This Row],[revenue]]>=2000,"Mega Hit", Movie_financials__with_release_date[[#This Row],[revenue]]>=1000,"Super Hit", Movie_financials__with_release_date[[#This Row],[revenue]]>=500,"Hit", TRUE,"Average")} -> Mega Hit | V19: =IF(AND(Movie_financials__with_release_date[[#This Row],[budget]]>=200,Movie_financials__with_release_date[[#This Row],[profit_category]]="Low Profit"),"⚠ Review","OK") -> OK
A20: 120 | B20: The Godfather | C20: Hollywood | D20: 1972 | E20: 9.2 | F20: Paramount Pictures | G20: 5 | H20: 7 | I20: 291 | J20: Millions | K20: USD | L20: 26382 | M20: {=_xlfn.IFS( Movie_financials__with_release_date[[#This Row],[revenue]]<500,"Average", Movie_financials__with_release_date[[#This Row],[revenue]]<=1000,"Hit", TRUE,"Blockbuster")} -> Average | N20: {=_xlfn.IFS(Movie_financials__with_release_date[[#This Row],[imdb_rating]]<7,"Average",Movie_financials__with_release_date[[#This Row],[imdb_rating]]<=8.5,"Good",TRUE,"Excellent")} -> Excellent | O20: {=_xlfn.IFS(Movie_financials__with_release_date[[#This Row],[budget]]<50,"Low budget",Movie_financials__with_release_date[[#This Row],[budget]]<=150,"Medium budget",TRUE,"High budget")} -> Low budget | P20: =DATEDIF(Movie_financials__with_release_date[[#This Row],[release_date]],TODAY(),"Y")& "years"& DATEDIF(Movie_financials__with_release_date[[#This Row],[release_date]],TODAY(),"YM")& "months" -> 54years3months | Q20: =DATEDIF(Movie_financials__with_release_date[[#This Row],[release_date]],TODAY(),"Y") -> 54 | R20: {=_xlfn.IFS(Movie_financials__with_release_date[[#This Row],[Movie_age(years)]]<5,"New Release",Movie_financials__with_release_date[[#This Row],[Movie_age(years)]]<=15,"Modern Classic", TRUE,"Classic" )} -> Classic | S20: {=_xlfn.IFS(Movie_financials__with_release_date[[#This Row],[revenue]]>Movie_financials__with_release_date[[#This Row],[budget]]*3,"Highly Profitable", Movie_financials__with_release_date[[#This Row],[revenue]]>Movie_financials__with_release_date[[#This Row],[budget]],"Profitable", TRUE,"Low Profit")} -> Highly Profitable | T20: {=_xlfn.IFS(Movie_financials__with_release_date[[#This Row],[imdb_rating]]>=9,"A+", Movie_financials__with_release_date[[#This Row],[imdb_rating]]>=8,"A", Movie_financials__with_release_date[[#This Row],[imdb_rating]]>=7,"B", TRUE,"C")} -> A+ | U20: {=_xlfn.IFS(Movie_financials__with_release_date[[#This Row],[revenue]]>=2000,"Mega Hit", Movie_financials__with_release_date[[#This Row],[revenue]]>=1000,"Super Hit", Movie_financials__with_release_date[[#This Row],[revenue]]>=500,"Hit", TRUE,"Average")} -> Average | V20: =IF(AND(Movie_financials__with_release_date[[#This Row],[budget]]>=200,Movie_financials__with_release_date[[#This Row],[profit_category]]="Low Profit"),"⚠ Review","OK") -> OK
A21: 121 | B21: The Dark Knight | C21: Hollywood | D21: 2008 | E21: 9 | F21: Syncopy | G21: 5 | H21: 185 | I21: 1006 | J21: Millions | K21: USD | L21: 39647 | M21: {=_xlfn.IFS( Movie_financials__with_release_date[[#This Row],[revenue]]<500,"Average", Movie_financials__with_release_date[[#This Row],[revenue]]<=1000,"Hit", TRUE,"Blockbuster")} -> Blockbuster | N21: {=_xlfn.IFS(Movie_financials__with_release_date[[#This Row],[imdb_rating]]<7,"Average",Movie_financials__with_release_date[[#This Row],[imdb_rating]]<=8.5,"Good",TRUE,"Excellent")} -> Excellent | O21: {=_xlfn.IFS(Movie_financials__with_release_date[[#This Row],[budget]]<50,"Low budget",Movie_financials__with_release_date[[#This Row],[budget]]<=150,"Medium budget",TRUE,"High budget")} -> High budget | P21: =DATEDIF(Movie_financials__with_release_date[[#This Row],[release_date]],TODAY(),"Y")& "years"& DATEDIF(Movie_financials__with_release_date[[#This Row],[release_date]],TODAY(),"YM")& "months" -> 18years0months | Q21: =DATEDIF(Movie_financials__with_release_date[[#This Row],[release_date]],TODAY(),"Y") -> 18 | R21: {=_xlfn.IFS(Movie_financials__with_release_date[[#This Row],[Movie_age(years)]]<5,"New Release",Movie_financials__with_release_date[[#This Row],[Movie_age(years)]]<=15,"Modern Classic", TRUE,"Classic" )} -> Classic | S21: {=_xlfn.IFS(Movie_financials__with_release_date[[#This Row],[revenue]]>Movie_financials__with_release_date[[#This Row],[budget]]*3,"Highly Profitable", Movie_financials__with_release_date[[#This Row],[revenue]]>Movie_financials__with_release_date[[#This Row],[budget]],"Profitable", TRUE,"Low Profit")} -> Highly Profitable | T21: {=_xlfn.IFS(Movie_financials__with_release_date[[#This Row],[imdb_rating]]>=9,"A+", Movie_financials__with_release_date[[#This Row],[imdb_rating]]>=8,"A", Movie_financials__with_release_date[[#This Row],[imdb_rating]]>=7,"B", TRUE,"C")} -> A+ | U21: {=_xlfn.IFS(Movie_financials__with_release_date[[#This Row],[revenue]]>=2000,"Mega Hit", Movie_financials__with_release_date[[#This Row],[revenue]]>=1000,"Super Hit", Movie_financials__with_release_date[[#This Row],[revenue]]>=500,"Hit", TRUE,"Average")} -> Super Hit | V21: =IF(AND(Movie_financials__with_release_date[[#This Row],[budget]]>=200,Movie_financials__with_release_date[[#This Row],[profit_category]]="Low Profit"),"⚠ Review","OK") -> OK
A22: 122 | B22: Schindler's List | C22: Hollywood | D22: 1993 | E22: 9 | F22: Universal Pictures | G22: 5 | H22: 22 | I22: 322.2 | J22: Millions | K22: USD | L22: 34004 | M22: {=_xlfn.IFS( Movie_financials__with_release_date[[#This Row],[revenue]]<500,"Average", Movie_financials__with_release_date[[#This Row],[revenue]]<=1000,"Hit", TRUE,"Blockbuster")} -> Average | N22: {=_xlfn.IFS(Movie_financials__with_release_date[[#This Row],[imdb_rating]]<7,"Average",Movie_financials__with_release_date[[#This Row],[imdb_rating]]<=8.5,"Good",TRUE,"Excellent")} -> Excellent | O22: {=_xlfn.IFS(Movie_financials__with_release_date[[#This Row],[budget]]<50,"Low budget",Movie_financials__with_release_date[[#This Row],[budget]]<=150,"Medium budget",TRUE,"High budget")} -> Low budget | P22: =DATEDIF(Movie_financials__with_release_date[[#This Row],[release_date]],TODAY(),"Y")& "years"& DATEDIF(Movie_financials__with_release_date[[#This Row],[release_date]],TODAY(),"YM")& "months" -> 33years5months | Q22: =DATEDIF(Movie_financials__with_release_date[[#This Row],[release_date]],TODAY(),"Y") -> 33 | R22: {=_xlfn.IFS(Movie_financials__with_release_date[[#This Row],[Movie_age(years)]]<5,"New Release",Movie_financials__with_release_date[[#This Row],[Movie_age(years)]]<=15,"Modern Classic", TRUE,"Classic" )} -> Classic | S22: {=_xlfn.IFS(Movie_financials__with_release_date[[#This Row],[revenue]]>Movie_financials__with_release_date[[#This Row],[budget]]*3,"Highly Profitable", Movie_financials__with_release_date[[#This Row],[revenue]]>Movie_financials__with_release_date[[#This Row],[budget]],"Profitable", TRUE,"Low Profit")} -> Highly Profitable | T22: {=_xlfn.IFS(Movie_financials__with_release_date[[#This Row],[imdb_rating]]>=9,"A+", Movie_financials__with_release_date[[#This Row],[imdb_rating]]>=8,"A", Movie_financials__with_release_date[[#This Row],[imdb_rating]]>=7,"B", TRUE,"C")} -> A+ | U22: {=_xlfn.IFS(Movie_financials__with_release_date[[#This Row],[revenue]]>=2000,"Mega Hit", Movie_financials__with_release_date[[#This Row],[revenue]]>=1000,"Super Hit", Movie_financials__with_release_date[[#This Row],[revenue]]>=500,"Hit", TRUE,"Average")} -> Average | V22: =IF(AND(Movie_financials__with_release_date[[#This Row],[budget]]>=200,Movie_financials__with_release_date[[#This Row],[profit_category]]="Low Profit"),"⚠ Review","OK") -> OK
A23: 123 | B23: Jurassic Park | C23: Hollywood | D23: 1993 | E23: 8.2 | F23: Universal Pictures | G23: 5 | H23: 63 | I23: 1046 | J23: Millions | K23: USD | L23: 34131 | M23: {=_xlfn.IFS( Movie_financials__with_release_date[[#This Row],[revenue]]<500,"Average", Movie_financials__with_release_date[[#This Row],[revenue]]<=1000,"Hit", TRUE,"Blockbuster")} -> Blockbuster | N23: {=_xlfn.IFS(Movie_financials__with_release_date[[#This Row],[imdb_rating]]<7,"Average",Movie_financials__with_release_date[[#This Row],[imdb_rating]]<=8.5,"Good",TRUE,"Excellent")} -> Good | O23: {=_xlfn.IFS(Movie_financials__with_release_date[[#This Row],[budget]]<50,"Low budget",Movie_financials__with_release_date[[#This Row],[budget]]<=150,"Medium budget",TRUE,"High budget")} -> Medium budget | P23: =DATEDIF(Movie_financials__with_release_date[[#This Row],[release_date]],TODAY(),"Y")& "years"& DATEDIF(Movie_financials__with_release_date[[#This Row],[release_date]],TODAY(),"YM")& "months" -> 33years1months | Q23: =DATEDIF(Movie_financials__with_release_date[[#This Row],[release_date]],TODAY(),"Y") -> 33 | R23: {=_xlfn.IFS(Movie_financials__with_release_date[[#This Row],[Movie_age(years)]]<5,"New Release",Movie_financials__with_release_date[[#This Row],[Movie_age(years)]]<=15,"Modern Classic", TRUE,"Classic" )} -> Classic | S23: {=_xlfn.IFS(Movie_financials__with_release_date[[#This Row],[revenue]]>Movie_financials__with_release_date[[#This Row],[budget]]*3,"Highly Profitable", Movie_financials__with_release_date[[#This Row],[revenue]]>Movie_financials__with_release_date[[#This Row],[budget]],"Profitable", TRUE,"Low Profit")} -> Highly Profitable | T23: {=_xlfn.IFS(Movie_financials__with_release_date[[#This Row],[imdb_rating]]>=9,"A+", Movie_financials__with_release_date[[#This Row],[imdb_rating]]>=8,"A", Movie_financials__with_release_date[[#This Row],[imdb_rating]]>=7,"B", TRUE,"C")} -> A | U23: {=_xlfn.IFS(Movie_financials__with_release_date[[#This Row],[revenue]]>=2000,"Mega Hit", Movie_financials__with_release_date[[#This Row],[revenue]]>=1000,"Super Hit", Movie_financials__with_release_date[[#This Row],[revenue]]>=500,"Hit", TRUE,"Average")} -> Super Hit | V23: =IF(AND(Movie_financials__with_release_date[[#This Row],[budget]]>=200,Movie_financials__with_release_date[[#This Row],[profit_category]]="Low Profit"),"⚠ Review","OK") -> OK
A24: 124 | B24: Parasite | C24: Hollywood | D24: 2019 | E24: 8.5 | F24: Not Avialable | G24: 5 | H24: 16 | I24: 263.1 | J24: Millions | K24: USD | L24: 43615 | M24: {=_xlfn.IFS( Movie_financials__with_release_date[[#This Row],[revenue]]<500,"Average", Movie_financials__with_release_date[[#This Row],[revenue]]<=1000,"Hit", TRUE,"Blockbuster")} -> Average | N24: {=_xlfn.IFS(Movie_financials__with_release_date[[#This Row],[imdb_rating]]<7,"Average",Movie_financials__with_release_date[[#This Row],[imdb_rating]]<=8.5,"Good",TRUE,"Excellent")} -> Good | O24: {=_xlfn.IFS(Movie_financials__with_release_date[[#This Row],[budget]]<50,"Low budget",Movie_financials__with_release_date[[#This Row],[budget]]<=150,"Medium budget",TRUE,"High budget")} -> Low budget | P24: =DATEDIF(Movie_financials__with_release_date[[#This Row],[release_date]],TODAY(),"Y")& "years"& DATEDIF(Movie_financials__with_release_date[[#This Row],[release_date]],TODAY(),"YM")& "months" -> 7years1months | Q24: =DATEDIF(Movie_financials__with_release_date[[#This Row],[release_date]],TODAY(),"Y") -> 7 | R24: {=_xlfn.IFS(Movie_financials__with_release_date[[#This Row],[Movie_age(years)]]<5,"New Release",Movie_financials__with_release_date[[#This Row],[Movie_age(years)]]<=15,"Modern Classic", TRUE,"Classic" )} -> Modern Classic | S24: {=_xlfn.IFS(Movie_financials__with_release_date[[#This Row],[revenue]]>Movie_financials__with_release_date[[#This Row],[budget]]*3,"Highly Profitable", Movie_financials__with_release_date[[#This Row],[revenue]]>Movie_financials__with_release_date[[#This Row],[budget]],"Profitable", TRUE,"Low Profit")} -> Highly Profitable | T24: {=_xlfn.IFS(Movie_financials__with_release_date[[#This Row],[imdb_rating]]>=9,"A+", Movie_financials__with_release_date[[#This Row],[imdb_rating]]>=8,"A", Movie_financials__with_release_date[[#This Row],[imdb_rating]]>=7,"B", TRUE,"C")} -> A | U24: {=_xlfn.IFS(Movie_financials__with_release_date[[#This Row],[revenue]]>=2000,"Mega Hit", Movie_financials__with_release_date[[#This Row],[revenue]]>=1000,"Super Hit", Movie_financials__with_release_date[[#This Row],[revenue]]>=500,"Hit", TRUE,"Average")} -> Average | V24: =IF(AND(Movie_financials__with_release_date[[#This Row],[budget]]>=200,Movie_financials__with_release_date[[#This Row],[profit_category]]="Low Profit"),"⚠ Review","OK") -> OK
A25: 125 | B25: Avengers: Endgame | C25: Hollywood | D25: 2019 | E25: 8.4 | F25: Marvel Studios | G25: 5 | H25: 400 | I25: 2798 | J25: Millions | K25: USD | L25: 43584 | M25: {=_xlfn.IFS( Movie_financials__with_release_date[[#This Row],[revenue]]<500,"Average", Movie_financials__with_release_date[[#This Row],[revenue]]<=1000,"Hit", TRUE,"Blockbuster")} -> Blockbuster | N25: {=_xlfn.IFS(Movie_financials__with_release_date[[#This Row],[imdb_rating]]<7,"Average",Movie_financials__with_release_date[[#This Row],[imdb_rating]]<=8.5,"Good",TRUE,"Excellent")} -> Good | O25: {=_xlfn.IFS(Movie_financials__with_release_date[[#This Row],[budget]]<50,"Low budget",Movie_financials__with_release_date[[#This Row],[budget]]<=150,"Medium budget",TRUE,"High budget")} -> High budget | P25: =DATEDIF(Movie_financials__with_release_date[[#This Row],[release_date]],TODAY(),"Y")& "years"& DATEDIF(Movie_financials__with_release_date[[#This Row],[release_date]],TODAY(),"YM")& "months" -> 7years2months | Q25: =DATEDIF(Movie_financials__with_release_date[[#This Row],[release_date]],TODAY(),"Y") -> 7 | R25: {=_xlfn.IFS(Movie_financials__with_release_date[[#This Row],[Movie_age(years)]]<5,"New Release",Movie_financials__with_release_date[[#This Row],[Movie_age(years)]]<=15,"Modern Classic", TRUE,"Classic" )} -> Modern Classic | S25: {=_xlfn.IFS(Movie_financials__with_release_date[[#This Row],[revenue]]>Movie_financials__with_release_date[[#This Row],[budget]]*3,"Highly Profitable", Movie_financials__with_release_date[[#This Row],[revenue]]>Movie_financials__with_release_date[[#This Row],[budget]],"Profitable", TRUE,"Low Profit")} -> Highly Profitable | T25: {=_xlfn.IFS(Movie_financials__with_release_date[[#This Row],[imdb_rating]]>=9,"A+", Movie_financials__with_release_date[[#This Row],[imdb_rating]]>=8,"A", Movie_financials__with_release_date[[#This Row],[imdb_rating]]>=7,"B", TRUE,"C")} -> A | U25: {=_xlfn.IFS(Movie_financials__with_release_date[[#This Row],[revenue]]>=2000,"Mega Hit", Movie_financials__with_release_date[[#This Row],[revenue]]>=1000,"Super Hit", Movie_financials__with_release_date[[#This Row],[revenue]]>=500,"Hit", TRUE,"Average")} -> Mega Hit | V25: =IF(AND(Movie_financials__with_release_date[[#This Row],[budget]]>=200,Movie_financials__with_release_date[[#This Row],[profit_category]]="Low Profit"),"⚠ Review","OK") -> OK
A26: 126 | B26: Avengers: Infinity War | C26: Hollywood | D26: 2018 | E26: 8.4 | F26: Marvel Studios | G26: 5 | H26: 400 | I26: 2048 | J26: Millions | K26: USD | L26: 43217 | M26: {=_xlfn.IFS( Movie_financials__with_release_date[[#This Row],[revenue]]<500,"Average", Movie_financials__with_release_date[[#This Row],[revenue]]<=1000,"Hit", TRUE,"Blockbuster")} -> Blockbuster | N26: {=_xlfn.IFS(Movie_financials__with_release_date[[#This Row],[imdb_rating]]<7,"Average",Movie_financials__with_release_date[[#This Row],[imdb_rating]]<=8.5,"Good",TRUE,"Excellent")} -> Good | O26: {=_xlfn.IFS(Movie_financials__with_release_date[[#This Row],[budget]]<50,"Low budget",Movie_financials__with_release_date[[#This Row],[budget]]<=150,"Medium budget",TRUE,"High budget")} -> High budget | P26: =DATEDIF(Movie_financials__with_release_date[[#This Row],[release_date]],TODAY(),"Y")& "years"& DATEDIF(Movie_financials__with_release_date[[#This Row],[release_date]],TODAY(),"YM")& "months" -> 8years2months | Q26: =DATEDIF(Movie_financials__with_release_date[[#This Row],[release_date]],TODAY(),"Y") -> 8 | R26: {=_xlfn.IFS(Movie_financials__with_release_date[[#This Row],[Movie_age(years)]]<5,"New Release",Movie_financials__with_release_date[[#This Row],[Movie_age(years)]]<=15,"Modern Classic", TRUE,"Classic" )} -> Modern Classic | S26: {=_xlfn.IFS(Movie_financials__with_release_date[[#This Row],[revenue]]>Movie_financials__with_release_date[[#This Row],[budget]]*3,"Highly Profitable", Movie_financials__with_release_date[[#This Row],[revenue]]>Movie_financials__with_release_date[[#This Row],[budget]],"Profitable", TRUE,"Low Profit")} -> Highly Profitable | T26: {=_xlfn.IFS(Movie_financials__with_release_date[[#This Row],[imdb_rating]]>=9,"A+", Movie_financials__with_release_date[[#This Row],[imdb_rating]]>=8,"A", Movie_financials__with_release_date[[#This Row],[imdb_rating]]>=7,"B", TRUE,"C")} -> A | U26: {=_xlfn.IFS(Movie_financials__with_release_date[[#This Row],[revenue]]>=2000,"Mega Hit", Movie_financials__with_release_date[[#This Row],[revenue]]>=1000,"Super Hit", Movie_financials__with_release_date[[#This Row],[revenue]]>=500,"Hit", TRUE,"Average")} -> Mega Hit | V26: =IF(AND(Movie_financials__with_release_date[[#This Row],[budget]]>=200,Movie_financials__with_release_date[[#This Row],[profit_category]]="Low Profit"),"⚠ Review","OK") -> OK
... A40: 140 | B40: Shershaah | C40: Bollywood | D40: 2021 | E40: 8.4 | F40: Dharma Productions | G40: 1 | H40: 500 | I40: 950 | J40: Millions | K40: INR | L40: 44420 | M40: {=_xlfn.IFS( Movie_financials__with_release_date[[#This Row],[revenue]]<500,"Average", Movie_financials__with_release_date[[#This Row],[revenue]]<=1000,"Hit", TRUE,"Blockbuster")} -> Hit | N40: {=_xlfn.IFS(Movie_financials__with_release_date[[#This Row],[imdb_rating]]<7,"Average",Movie_financials__with_release_date[[#This Row],[imdb_rating]]<=8.5,"Good",TRUE,"Excellent")} -> Good | O40: {=_xlfn.IFS(Movie_financials__with_release_date[[#This Row],[budget]]<50,"Low budget",Movie_financials__with_release_date[[#This Row],[budget]]<=150,"Medium budget",TRUE,"High budget")} -> High budget | P40: =DATEDIF(Movie_financials__with_release_date[[#This Row],[release_date]],TODAY(),"Y")& "years"& DATEDIF(Movie_financials__with_release_date[[#This Row],[release_date]],TODAY(),"YM")& "months" -> 4years11months | Q40: =DATEDIF(Movie_financials__with_release_date[[#This Row],[release_date]],TODAY(),"Y") -> 4 | R40: {=_xlfn.IFS(Movie_financials__with_release_date[[#This Row],[Movie_age(years)]]<5,"New Release",Movie_financials__with_release_date[[#This Row],[Movie_age(years)]]<=15,"Modern Classic", TRUE,"Classic" )} -> New Release | S40: {=_xlfn.IFS(Movie_financials__with_release_date[[#This Row],[revenue]]>Movie_financials__with_release_date[[#This Row],[budget]]*3,"Highly Profitable", Movie_financials__with_release_date[[#This Row],[revenue]]>Movie_financials__with_release_date[[#This Row],[budget]],"Profitable", TRUE,"Low Profit")} -> Profitable | T40: {=_xlfn.IFS(Movie_financials__with_release_date[[#This Row],[imdb_rating]]>=9,"A+", Movie_financials__with_release_date[[#This Row],[imdb_rating]]>=8,"A", Movie_financials__with_release_date[[#This Row],[imdb_rating]]>=7,"B", TRUE,"C")} -> A | U40: {=_xlfn.IFS(Movie_financials__with_release_date[[#This Row],[revenue]]>=2000,"Mega Hit", Movie_financials__with_release_date[[#This Row],[revenue]]>=1000,"Super Hit", Movie_financials__with_release_date[[#This Row],[revenue]]>=500,"Hit", TRUE,"Average")} -> Hit | V40: =IF(AND(Movie_financials__with_release_date[[#This Row],[budget]]>=200,Movie_financials__with_release_date[[#This Row],[profit_category]]="Low Profit"),"⚠ Review","OK") -> OK

Sheet Day5 pivot table 1
A3: Movie era distribution
A5: studio | B5: (All)
A7: Movie_era | B7: Movie_count
A8: Classic | B8: 17
A9: Modern Classic | B9: 15
A10: New Release | B10: 7
A11: Grand Total | B11: 39

Sheet Day5 pivot table 2
A3: Movie age distribution by industry
A7: * | B7: Movie_count
A8: Industry | B8: Classic | C8: Modern Classic | D8: New Release | E8: Grand Total
A9: Bollywood | B9: 7 | C9: 6 | D9: 5 | E9: 18
A10: Hollywood | B10: 10 | C10: 9 | D10: 2 | E10: 21
A11: Grand Total | B11: 17 | C11: 15 | D11: 7 | E11: 39

Sheet Day 6 pivot table 1
A3: Highest priority
A7: profit_category | B7: Movie_count
A8: Highly Profitable | B8: 28
A9: Low Profit | B9: 2
A10: Profitable | B10: 9
A11: Grand Total | B11: 39

Sheet Day 6 pivot table 2
A3: Quality vs revenue analysis
A7: *
A8: Imdb_grade | B8: Average | C8: Hit | D8: Mega Hit | E8: Super Hit | F8: Grand Total
A9: A | B9: 11 | C9: 2 | D9: 7 | E9: 2 | F9: 22
A10: A+ | B10: 3 | E10: 1 | F10: 4
A11: B | B11: 2 | C11: 3 | D11: 2 | E11: 1 | F11: 8
A12: C | B12: 3 | C12: 2 | F12: 5
A13: Grand Total | B13: 19 | C13: 7 | D13: 9 | E13: 4 | F13: 39

Sheet Day 6 pivot table 3
A3: Industry profitability comparison
A7: *
A8: Industry | B8: Highly Profitable | C8: Low Profit | D8: Profitable | E8: Grand Total
A9: Bollywood | B9: 12 | C9: 1 | D9: 5 | E9: 18
A10: Hollywood | B10: 16 | C10: 1 | D10: 4 | E10: 21
A11: Grand Total | B11: 28 | C11: 2 | D11: 9 | E11: 39

Sheet DAY 7
A1: MOVIE BUSINESS DASHBOARD
E2: High Revenue but low Profit Analysis
H3: =COUNTIF(Movie_financials__with_release_date[revenue_category],"Mega Hit") -> 9
D4: =COUNT(Movie_financials__with_release_date[Movie_id]) -> 39
D5: =COUNTIF(Movie_financials__with_release_date[profit_category],"Low Profit") -> 2
D6: =COUNTIFS(Movie_financials__with_release_date[revenue_category],"Mega Hit",Movie_financials__with_release_date[profit_category],"Low Profit") -> 0
H8: =AVERAGE(Movie_financials__with_release_date[imdb_rating]) -> 7.7435897
A9: ⚠ Movies Requiring Management Review
A10: Title | B10: budget | C10: revenue | D10: Column1 | E10: profit_category | F10: Status
A11: Doctor Strange in the Multiverse of Madness | B11: 200 | C11: 954.8 | E11: Highly Profitable | F11: OK
A12: Thor: The Dark World | B12: 165 | C12: 644.8 | E12: Highly Profitable | F12: OK
A13: Thor: Ragnarok | B13: 180 | C13: 854 | E13: Highly Profitable | F13: OK
A14: Thor: Love and Thunder | B14: 250 | C14: 670 | E14: Profitable | F14: OK
A15: Dilwale Dulhania Le Jayenge | B15: 400 | C15: 2000 | E15: Highly Profitable | F15: OK
A16: 3 Idiots | B16: 550 | C16: 4000 | E16: Highly Profitable | F16: OK
A17: Kabhi Khushi Kabhie Gham | B17: 390 | C17: 1360 | E17: Highly Profitable | F17: OK
A18: Interstellar | B18: 165 | C18: 701.8 | E18: Highly Profitable | F18: OK
A19: Titanic | B19: 200 | C19: 2202 | E19: Highly Profitable | F19: OK
A20: Avatar | B20: 237 | C20: 2847 | E20: Highly Profitable | F20: OK
A21: The Dark Knight | B21: 185 | C21: 1006 | E21: Highly Profitable | F21: OK
A22: Avengers: Endgame | B22: 400 | C22: 2798 | E22: Highly Profitable | F22: OK
... A29: Shershaah | B29: 500 | C29: 950 | E29: Profitable | F29: OK

Sheet DAY 8
B1: DAY 8 - SUMIFS Bussiness Questions
A5: S.no | B5: Bussiness questions | C5: Result(Revenue) | E5: Formula demonstration
A6: 1 | B6: Total Hollywood Revenue | C6: =SUMIFS(Movie_financials__with_release_date[revenue],Movie_financials__with_release_date[industry],"Hollywood") -> 18577.9 | F6: Total Hollywood Revenue
A7: 2 | B7: Total Bollywood Revenue | C7: =SUMIFS(Movie_financials__with_release_date[revenue],Movie_financials__with_release_date[industry],"Bollywood") -> 33856.1 | H7: =SUMIFS(Movie_financials__with_release_date[revenue],Movie_financials__with_release_date[industry],"Hollywood") -> 18577.9
A8: 3 | B8: Total Hit movies Revenue | C8: =SUMIFS(Movie_financials__with_release_date[revenue],Movie_financials__with_release_date[Movie_performance],"Hit") -> 5489.8
A9: 4 | B9: Total High Budget Revenue | C9: =SUMIFS(Movie_financials__with_release_date[revenue],Movie_financials__with_release_date[Budget_category],"High budget") -> 47760.4
A10: 5 | B10: Hollywood + High Budget + Hit | C10: =SUMIFS(Movie_financials__with_release_date[revenue],Movie_financials__with_release_date[industry],"Hollywood",Movie_financials__with_release_date[Budget_category],"High budget",Movie_financials__with_release_date[Movie_performance],"Hit") -> 4539.8
A11: 6 | B11: Hollywood + High Budget + Hit + Excellent | C11: =SUMIFS(Movie_financials__with_release_date[revenue],Movie_financials__with_release_date[industry],"Hollywood",Movie_financials__with_release_date[Budget_category],"High budget",Movie_financials__with_release_date[Movie_performance],"Hit",Movie_financials__with_release_date[Rating_category],"Excellent") -> 701.8
B13: Key take aways
B14: ✅ SUMIFS syntax: SUMIFS(sum_range, criteria_range1, criteria1, ...)
B15: ✅ Always remember: Sum first, Conditions after.
B16: ✅ Use SUMIF for one condition and SUMIFS for one or more conditions.
B17: ✅ SUMIFS uses AND logic (all conditions must be true).

Sheet DAY 9
A1: DAY 9 - INDEX MATCH(Looking left)
A2: Movie Table | I2: Finance Table
A3: studio | B3: industry | C3: imdb_rating | D3: Movie_id | E3: language_id | I3: movie_id | J3: budget | K3: revenue | L3: unit | M3: currency | N3: Studio
A4: Hombale Films | B4: Bollywood | C4: 8.4 | D4: 101 | E4: 3 | I4: 101 | J4: 1 | K4: 12.5 | L4: Billions | M4: INR | N4: =INDEX(Table17[studio],MATCH(Table18[[#This Row],[movie_id]],Table17[Movie_id],0)) -> Hombale Films
A5: Marvel Studios | B5: Hollywood | C5: 7 | D5: 102 | E5: 5 | I5: 102 | J5: 200 | K5: 954.8 | L5: Millions | M5: USD | N5: =INDEX(Table17[studio],MATCH(Table18[[#This Row],[movie_id]],Table17[Movie_id],0)) -> Marvel Studios
A6: Marvel Studios | B6: Hollywood | C6: 6.8 | D6: 103 | E6: 5 | I6: 103 | J6: 165 | K6: 644.8 | L6: Millions | M6: USD | N6: =INDEX(Table17[studio],MATCH(Table18[[#This Row],[movie_id]],Table17[Movie_id],0)) -> Marvel Studios
A7: Marvel Studios | B7: Hollywood | C7: 7.9 | D7: 104 | E7: 5 | I7: 104 | J7: 180 | K7: 854 | L7: Millions | M7: USD | N7: =INDEX(Table17[studio],MATCH(Table18[[#This Row],[movie_id]],Table17[Movie_id],0)) -> Marvel Studios
A8: Marvel Studios | B8: Hollywood | C8: 6.8 | D8: 105 | E8: 5 | I8: 105 | J8: 250 | K8: 670 | L8: Millions | M8: USD | N8: =INDEX(Table17[studio],MATCH(Table18[[#This Row],[movie_id]],Table17[Movie_id],0)) -> Marvel Studios
A9: United Producers | B9: Bollywood | C9: 8.1 | D9: 106 | E9: 1 | I9: 107 | J9: 400 | K9: 2000 | L9: Millions | M9: INR | N9: =INDEX(Table17[studio],MATCH(Table18[[#This Row],[movie_id]],Table17[Movie_id],0)) -> Yash Raj Films
A10: Yash Raj Films | B10: Bollywood | C10: 8 | D10: 107 | E10: 1 | I10: 108 | J10: 550 | K10: 4000 | L10: Millions | M10: INR | N10: =INDEX(Table17[studio],MATCH(Table18[[#This Row],[movie_id]],Table17[Movie_id],0)) -> Vinod Chopra Films
A11: Vinod Chopra Films | B11: Bollywood | C11: 8.4 | D11: 108 | E11: 1 | I11: 109 | J11: 390 | K11: 1360 | L11: Millions | M11: INR | N11: =INDEX(Table17[studio],MATCH(Table18[[#This Row],[movie_id]],Table17[Movie_id],0)) -> Dharma Productions
A12: Dharma Productions | B12: Bollywood | C12: 7.4 | D12: 109 | E12: 1 | I12: 110 | J12: 1.4 | K12: 3.5 | L12: Billions | M12: INR | N12: =INDEX(Table17[studio],MATCH(Table18[[#This Row],[movie_id]],Table17[Movie_id],0)) -> #N/A
N14: =INDEX(Table17[studio],MATCH(Table18[[#This Row],[movie_id]],Table17[Movie_id],0)) -> #N/A

Sheet Day 10 power query editor
A1: Source.Name | B1: Movie_id | C1: Title | D1: industry | E1: release_year | F1: imdb_rating | G1: studio | H1: revenue
A2: Movie_apr.xlsx | B2: 109 | C2: Kabhi Khushi Kabhie Gham | D2: Bollywood | E2: 2001 | F2: 7.4 | G2: Dharma Productions | H2: 1360
A3: Movie_apr.xlsx | B3: 110 | C3: Bajirao Mastani | D3: Bollywood | E3: 2015 | F3: 7.2 | G3: Not Avialable | H3: 3.5
A4: Movie_apr.xlsx | B4: 129 | C4: Munna Bhai M.B.B.S. | D4: Bollywood | E4: 2003 | F4: 8.1 | G4: Vinod Chopra Productions | H4: 100
A5: Movie_apr.xlsx | B5: 130 | C5: PK | D5: Bollywood | E5: 2014 | F5: 8.1 | G5: Vinod Chopra Films | H5: 850
A6: Movie_apr.xlsx | B6: 131 | C6: Sanju | D6: Bollywood | E6: 2018 | F6: 0 | G6: Vinod Chopra Films | H6: 1
A7: Movie_apr.xlsx | B7: 132 | C7: Pushpa: The Rise - Part 1 | D7: Bollywood | E7: 2021 | F7: 7.6 | G7: Mythri Movie Makers | H7: 2
A8: Movie_apr.xlsx | B8: 133 | C8: RRR | D8: Bollywood | E8: 2022 | F8: 8 | G8: DVV Entertainment | H8: 6
A9: Movie_apr.xlsx | B9: 134 | C9: Baahubali: The Beginning | D9: Bollywood | E9: 2015 | F9: 8 | G9: Arka Media Works | H9: 2
A10: Movie_apr.xlsx | B10: 135 | C10: The Kashmir Files | D10: Bollywood | E10: 2022 | F10: 8.3 | G10: Zee Studios | H10: 250
A11: Movie_apr.xlsx | B11: 125 | C11: Avengers: Endgame | D11: Hollywood | E11: 2019 | F11: 8.4 | G11: Marvel Studios | H11: 2798
A12: Movie_feb.xlsx | B12: 107 | C12: Dilwale Dulhania Le Jayenge | D12: Bollywood | E12: 1995 | F12: 8 | G12: Yash Raj Films | H12: 2000
A13: Movie_feb.xlsx | B13: 105 | C13: Thor: Love and Thunder | D13: Hollywood | E13: 2022 | F13: 6.8 | G13: Marvel Studios | H13: 670
... A15: Movie_feb.xlsx | B15: 113 | C15: Interstellar | D15: Hollywood | E15: 2014 | F15: 8.6 | G15: Warner Bros. Pictures | H15: 701.8
A16: Movie_feb.xlsx | B16: 112 | C16: Inception | D16: Hollywood | E16: 2010 | F16: 8.8 | G16: Warner Bros. Pictures
A17: Movie_feb.xlsx | B17: 115 | C17: The Pursuit of Happyness | D17: Hollywood | E17: 2006 | F17: 8 | G17: Columbia Pictures | H17: 307.1
A18: Movie_feb.xlsx | B18: 116 | C18: Gladiator | D18: Hollywood | E18: 2000 | F18: 8.5 | G18: Universal Pictures | H18: 460.5
A19: Movie_feb.xlsx | B19: 117 | C19: Titanic | D19: Hollywood | E19: 1997 | F19: 7.9 | G19: Paramount Pictures | H19: 2202
A20: Movie_feb.xlsx | B20: 118 | C20: It's a Wonderful Life | D20: Hollywood | E20: 1946 | F20: 8.6 | G20: Liberty Films | H20: 3.3
A21: Movie_jan.xlsx | B21: 101 | C21: K.G.F: Chapter 2 | D21: Bollywood | E21: 2022 | F21: 8.4 | G21: Hombale Films | H21: 12.5
A22: Movie_jan.xlsx | B22: 102 | C22: Doctor Strange in the Multiverse of Madness | D22: Hollywood | E22: 2022 | F22: 7 | G22: Marvel Studios | H22: 954.8
A23: Movie_jan.xlsx | B23: 103 | C23: Thor: The Dark World | D23: Hollywood | E23: 2013 | F23: 6.8 | G23: Marvel Studios | H23: 644.8
A24: Movie_jan.xlsx | B24: 104 | C24: Thor: Ragnarok | D24: Hollywood | E24: 2017 | F24: 7.9 | G24: Marvel Studios | H24: 854
A25: Movie_jan.xlsx | B25: 106 | C25: Sholay | D25: Bollywood | E25: 1975 | F25: 8.1 | G25: United Producers
A26: Movie_jan.xlsx | B26: 108 | C26: 3 Idiots | D26: Bollywood | E26: 2009 | F26: 8.4 | G26: Vinod Chopra Films | H26: 4000
A27: Movie_mar.xlsx | B27: 120 | C27: The Godfather | D27: Hollywood | E27: 1972 | F27: 9.2 | G27: Paramount Pictures | H27: 291
A28: Movie_mar.xlsx | B28: 121 | C28: The Dark Knight | D28: Hollywood | E28: 2008 | F28: 9 | G28: Syncopy | H28: 1006
A29: Movie_mar.xlsx | B29: 122 | C29: Schindler's List | D29: Hollywood | E29: 1993 | F29: 9 | G29: Universal Pictures | H29: 322.2
A30: Movie_mar.xlsx | B30: 123 | C30: Jurassic Park | D30: Hollywood | E30: 1993 | F30: 8.2 | G30: Universal Pictures | H30: 1046
A31: Movie_mar.xlsx | B31: 124 | C31: Parasite | D31: Hollywood | E31: 2019 | F31: 8.5 | G31: Not Avialable | H31: 263.1
A32: Movie_mar.xlsx | B32: 126 | C32: Avengers: Infinity War | D32: Hollywood | E32: 2018 | F32: 8.4 | G32: Marvel Studios | H32: 2048

Sheet DAY 10

Sheet DAY 11
A1: DAY 11 -DYNAMIC ARRAY DASHBOARD
A4: S NO | B4: Bussiness Questions | C4: Dynamic Report | D4: Function Used | E4: RESULT
A5: 1 | B5: How many unique studios do we have? | C5: All Unique Studios | D5: UNIQUE | E5: DAY 11'!B47
A6: 2 | B6: Show movies in alphabetical order | C6: Top Movies | D6: SORT | E6: DAY 11'!C55
A7: 3 | B7: Show only Hollywood movies. | C7: Hollywood Movies Only | D7: FILTER | E7: DAY 11'!D42
A8: 4 | B8: Sort movie titles using Revenue | C8: Revenue-wise Movie List | D8: SORTBY | E8: DAY 11'!B67
A9: 5 | B9: Show latest released movies | C9: Latest Released Movies | D9: TAKE + SORTBY | E9: DAY 11'!C68
A10: 6 | B10: Show Top 5 highest revenue movies | C10: First 5 Movies | D10: TAKE | E10: DAY 11'!E26
A11: 7 | B11: Ignore Top 5 movies | C11: Skip First 5 Movies | D11: DROP | E11: DAY 11'!D67
A12: 8 | B12: Management needs only key columns | C12: Selected Important Columns | D12: CHOOSECOLS | E12: DAY 11'!E67
A13: 9 | B13: Create automatic serial numbers | C13: Auto Movie Numbers | D13: SEQUENCE | E13: DAY 11'!B111
A14: 10 | B14: Management wants Hollywood and Bollywood combined | C14: Combine Hollywood + Bollywood | D14: VSTACK | E14: DAY 11'!C111
A15: 11 | B15: Suggest a movie of the day | C15: Random Movie Recommendation | D15: RANDARRAY | E15: DAY 11'!D111
A16: 12 | B16: Compare Revenue and Budget | C16: Revenue vs Budget Comparison | D16: HSTACK | E16: DAY 11'!E111
B26: All Unique Studios | C26: Top Movies | D26: Hollywood Movies Only | E26: First 5 Movies
B27: {=_xlfn.UNIQUE(Movie_financials__with_release_date[studio])} -> Hombale Films | C27: {=_xlfn._xlws.SORT(Movie_financials__with_release_date[Title])} -> 3 Idiots | D27: {=_xlfn._xlws.FILTER(Movie_financials__with_release_date[Title],Movie_financials__with_release_date[industry]="Hollywood")} -> Doctor Strange in the Multiverse of Madness | E27: {=_xlfn.TAKE(Movie_financials__with_release_date[Title],5)} -> K.G.F: Chapter 2
B28: Marvel Studios | C28: Avatar | D28: Thor: The Dark World | E28: Doctor Strange in the Multiverse of Madness
B29: United Producers | C29: Avengers: Endgame | D29: Thor: Ragnarok | E29: Thor: The Dark World
B30: Yash Raj Films | C30: Avengers: Infinity War | D30: Thor: Love and Thunder | E30: Thor: Ragnarok
B31: Vinod Chopra Films | C31: Baahubali: The Beginning | D31: The Shawshank Redemption | E31: Thor: Love and Thunder
B32: Dharma Productions | C32: Bajirao Mastani | D32: Interstellar
B33: Not Avialable | C33: Bajrangi Bhaijaan | D33: Inception
B34: Castle Rock Entertainment | C34: Captain America: The First Avenger | D34: The Pursuit of Happyness
B35: Warner Bros. Pictures | C35: Captain America: The Winter Soldier | D35: Gladiator
B36: Columbia Pictures | C36: Dilwale Dulhania Le Jayenge | D36: Titanic
B37: Universal Pictures | C37: Doctor Strange in the Multiverse of Madness | D37: It's a Wonderful Life
B38: Paramount Pictures | C38: Gladiator | D38: Avatar
B39: Liberty Films | C39: Inception | D39: The Godfather
B40: 20th Century Fox | C40: Interstellar | D40: The Dark Knight
B41: Syncopy | C41: It's a Wonderful Life | D41: Schindler's List
B42: Government of West Bengal | C42: Jurassic Park | D42: Jurassic Park
B43: Vinod Chopra Productions | C43: K.G.F: Chapter 2 | D43: Parasite
... B47: Zee Studios | C47: Pather Panchali | D47: Captain America: The Winter Soldier
B48: Salman Khan Films | C48: PK
C49: Pushpa: The Rise - Part 1
C50: Race 3
C51: RRR
C52: Sanju
C53: Schindler's List
C54: Shershaah
C55: Sholay
C56: Taare Zameen Par
C57: The Dark Knight
C58: The Godfather
C59: The Kashmir Files
C60: The Pursuit of Happyness
... C65: Titanic
B67: Revenue-wise Movie List | C67: Latest Released Movies | D67: Skip First 5 Movies | E67: Selected Important Columns
B68: {=_xlfn.SORTBY(Movie_financials__with_release_date[Title],Movie_financials__with_release_date[revenue],-1)} -> Bajrangi Bhaijaan | C68: {=_xlfn.TAKE( _xlfn.SORTBY( Movie_financials__with_release_date[Title], Movie_financials__with_release_date[release_year], -1), 5)} -> K.G.F: Chapter 2 | D68: {=_xlfn.DROP(Movie_financials__with_release_date[Title],5)} -> Sholay | E68: {=_xlfn.CHOOSECOLS( Movie_financials__with_release_date[], 6 )} -> Hombale Films
B69: PK | C69: Doctor Strange in the Multiverse of Madness | D69: Dilwale Dulhania Le Jayenge | E69: Marvel Studios
B70: 3 Idiots | C70: Thor: Love and Thunder | D70: 3 Idiots | E70: Marvel Studios
B71: The Kashmir Files | C71: RRR | D71: Kabhi Khushi Kabhie Gham | E71: Marvel Studios
B72: Avatar | C72: The Kashmir Files | D72: Bajirao Mastani | E72: Marvel Studios
B73: Avengers: Endgame | D73: The Shawshank Redemption | E73: United Producers
B74: Titanic | D74: Interstellar | E74: Yash Raj Films
B75: Avengers: Infinity War | D75: Inception | E75: Vinod Chopra Films
B76: Dilwale Dulhania Le Jayenge | D76: The Pursuit of Happyness | E76: Dharma Productions
B77: Kabhi Khushi Kabhie Gham | D77: Gladiator | E77: Not Avialable
B78: Taare Zameen Par | D78: Titanic | E78: Castle Rock Entertainment
B79: Jurassic Park | D79: It's a Wonderful Life | E79: Warner Bros. Pictures
B80: The Dark Knight | D80: Avatar | E80: Warner Bros. Pictures
B81: Doctor Strange in the Multiverse of Madness | D81: The Godfather | E81: Columbia Pictures
B82: Shershaah | D82: The Dark Knight | E82: Universal Pictures
B83: Thor: Ragnarok | D83: Schindler's List | E83: Paramount Pictures
B84: Captain America: The Winter Soldier | D84: Jurassic Park | E84: Liberty Films
... B101: Pushpa: The Rise - Part 1 | D101: Shershaah | E101: Zee Studios
B102: Bajirao Mastani | E102: Salman Khan Films
B103: It's a Wonderful Life | E103: Marvel Studios
B104: Race 3 | E104: Marvel Studios
B105: Sholay | E105: Salman Khan Films
B106: Inception | E106: Dharma Productions
B110: Auto Movie Numbers | C110: Combine Hollywood + Bollywood | D110: Random Movie Recommendation | E110: Revenue vs Budget Comparison
B111: {=_xlfn.SEQUENCE(ROWS(Movie_financials__with_release_date[]))} -> 1 | C111: {=_xlfn.VSTACK( _xlfn._xlws.FILTER(Movie_financials__with_release_date[Title], Movie_financials__with_release_date[industry]="Hollywood"), _xlfn._xlws.FILTER(Movie_financials__with_release_date[Title], Movie_financials__with_release_date[industry]="Bollywood") )} -> Doctor Strange in the Multiverse of Madness | D111: {=INDEX( Movie_financials__with_release_date[Title], _xlfn.RANDARRAY(1,1,1,ROWS(Movie_financials__with_release_date[]),TRUE) )} -> The Shawshank Redemption | E111: {=_xlfn.HSTACK( Movie_financials__with_release_date[Title], Movie_financials__with_release_date[budget] )} -> K.G.F: Chapter 2 | F111: 1
B112: 2 | C112: Thor: The Dark World | E112: Doctor Strange in the Multiverse of Madness | F112: 200
B113: 3 | C113: Thor: Ragnarok | E113: Thor: The Dark World | F113: 165
B114: 4 | C114: Thor: Love and Thunder | E114: Thor: Ragnarok | F114: 180
B115: 5 | C115: The Shawshank Redemption | E115: Thor: Love and Thunder | F115: 250
B116: 6 | C116: Interstellar | E116: Sholay | F116: 0
B117: 7 | C117: Inception | E117: Dilwale Dulhania Le Jayenge | F117: 400
B118: 8 | C118: The Pursuit of Happyness | E118: 3 Idiots | F118: 550
B119: 9 | C119: Gladiator | E119: Kabhi Khushi Kabhie Gham | F119: 390
B120: 10 | C120: Titanic | E120: Bajirao Mastani | F120: 1
B121: 11 | C121: It's a Wonderful Life | E121: The Shawshank Redemption | F121: 25
B122: 12 | C122: Avatar | E122: Interstellar | F122: 165
B123: 13 | C123: The Godfather | E123: Inception | F123: 0
... B149: 39 | C149: Shershaah | E149: Shershaah | F149: 500

Sheet DAY 12
A1: DAY 12 - GOAL SEEK & SCENARIO MANAGER
B3: Movie Analysis Dashboard
B4: Movie Name | D4: 3 Idoits
B5: Budget | D5: 550
B6: Current Revenue | D6: 4000
B7: Target Revenue | D7: 3500
B8: Expected units | D8: 5
B9: Ticket price | D9: 800
B10: Discount % | D10: 0.125
B11: Project Revenue | D11: =D8*D9*(1-D10) -> 3500
B12: Difference | D12: =D11-D7 -> 0
B14: Scenario Summary
C15: Conservative | D15: Moderate | E15: Aggressive
B16: Budget | C16: 550 | D16: 550 | E16: 550
B17: Discount % | C17: 0.05 | D17: 0.125 | E17: 0.18
B18: Project Revenue | C18: 800 | D18: 800 | E18: 800
B19: Profit/ loss | C19: =C18-C16 -> 250 | D19: =D18-D16 -> 250 | E19: =E18-E16 -> 250

Sheet Source_lists
A1: industry | B1: Bollywood studios | C1: Hollywood studios | D1: Movie name
A2: Bollywood | B2: Hombale Films | C2: Marvel Studios | D2: Captain America: The First Avenger
A3: Hollywood | B3: United Producers | C3: Castle Rock Entertainment | D3: Doctor Strange in the Multiverse of Madness
B4: Yash Raj Films | C4: Warner Bros. Pictures | D4: Thor: The Dark World
B5: Vinod Chopra Films | C5: Columbia Pictures | D5: Thor: Ragnarok
B6: Dharma Productions | C6: Universal Pictures | D6: Thor: Love and Thunder
B7: Government of West Bengal | C7: Paramount Pictures | D7: Avengers: Endgame
B8: Vinod Chopra Productions | C8: Liberty Films | D8: Avengers: Infinity War
B9: Mythri Movie Makers | C9: 20th Century Fox | D9: Captain America: The Winter Soldier
B10: DVV Entertainment | C10: Syncopy | D10: Kabhi Khushi Kabhie Gham
B11: Arka Media Works | D11: Bajirao Mastani
B12: Zee Studios | D12: The Shawshank Redemption
B13: Salman Khan Films | D13: Interstellar
D14: Inception
D15: The Pursuit of Happyness
D16: Gladiator
D17: Titanic
D18: It's a Wonderful Life
D19: Avatar
D20: The Godfather
D21: The Dark Knight
D22: Schindler's List
D23: Jurassic Park
D24: Parasite
D25: Sholay
... D44: Sanju

Sheet DAY 13
A1: DAY 13 - MOVIE SELECTOR DASHBOARD
B4: MOVIE SELECTOR | J4: Movie snapshot
B5: Select Industry | C5: Bollywood | J5: Field | K5: Value
B6: Select Studios | C6: Vinod Chopra Films | J6: Movie ID | K6: =_xlfn.XLOOKUP(C7,Movie_financials__with_release_date[Title],Movie_financials__with_release_date[Movie_id]) -> 108
B7: Select Movie | C7: 3 Idiots | J7: Release Date | K7: =_xlfn.XLOOKUP(C7,Movie_financials__with_release_date[Title],Movie_financials__with_release_date[release_date]) -> 40172
J8: Release Year | K8: =_xlfn.XLOOKUP(C7,Movie_financials__with_release_date[Title],Movie_financials__with_release_date[release_year]) -> 2009
B9: Movie Details | J9: Movie Age | K9: =_xlfn.XLOOKUP(C7,Movie_financials__with_release_date[Title],Movie_financials__with_release_date[Movie_age(years)]) -> 16
B10: Metric | C10: Value | J10: Movie Era | K10: =_xlfn.XLOOKUP(C7,Movie_financials__with_release_date[Title],Movie_financials__with_release_date[Movie_era]) -> Classic
B11: IMDb Rating | C11: =_xlfn.XLOOKUP(C7,Movie_financials__with_release_date[Title],Movie_financials__with_release_date[imdb_rating]) -> 8.4
B12: IMDb Grade | C12: =_xlfn.XLOOKUP(C7,Movie_financials__with_release_date[Title],Movie_financials__with_release_date[Imdb_grade]) -> A
B13: Budget | C13: =_xlfn.XLOOKUP(C7,Movie_financials__with_release_date[Title],Movie_financials__with_release_date[budget]) -> 550
B14: Revenue | C14: =_xlfn.XLOOKUP(C7,Movie_financials__with_release_date[Title],Movie_financials__with_release_date[revenue]) -> 4000
B15: Movie Performance | C15: =_xlfn.XLOOKUP(C7,Movie_financials__with_release_date[Title],Movie_financials__with_release_date[Movie_performance]) -> Blockbuster
B16: Rating Category | C16: =_xlfn.XLOOKUP(C7,Movie_financials__with_release_date[Title],Movie_financials__with_release_date[Rating_category]) -> Good
B17: Budget Category | C17: =_xlfn.XLOOKUP(C7,Movie_financials__with_release_date[Title],Movie_financials__with_release_date[Budget_category]) -> High budget
B18: Profit Category | C18: =_xlfn.XLOOKUP(C7,Movie_financials__with_release_date[Title],Movie_financials__with_release_date[profit_category]) -> Highly Profitable
B19: Revenue Category | C19: =_xlfn.XLOOKUP(C7,Movie_financials__with_release_date[Title],Movie_financials__with_release_date[revenue_category]) -> Mega Hit

Sheet DAY 14
A1: DAY 14 - VLOOKUP DEBUGGING
A3: Business Scenario:
B4: A finance report returned incorrect movie budgets after a VLOOKUP was used without proper precautions.
B5: This worksheet demonstrates how VLOOKUP can silently fail and how XLOOKUP and INDEX+MATCH provide safer alternatives.
A8: Movie_id | B8: Title | C8: VLOOKUP (Approximate) | D8: VLOOKUP (Exact Match) | E8: INDEX + MATCH | F8: Status | L8: Movie_id | M8: budget | N8: revenue
A9: 101 | B9: K.G.F: Chapter 2 | C9: =VLOOKUP(Table16[[#This Row],[Movie_id]],'DAY 14'!$L$8:$N$18,2) -> #N/A | D9: =VLOOKUP(Table16[[#This Row],[Movie_id]],'DAY 14'!$L$8:$N$18,2,FALSE) -> 1 | E9: =INDEX('DAY 14'!$M$9:$M$18,MATCH(A9,'DAY 14'!$L$9:$L$18,0)) -> 1 | F9: =IF(ISNA(C9),0, IF(C9=D9,1,-1)) -> 0 | L9: 102 | M9: 200 | N9: 954.8
A10: 102 | B10: Doctor Strange | C10: =VLOOKUP(Table16[[#This Row],[Movie_id]],'DAY 14'!$L$8:$N$18,2) -> 200 | D10: =VLOOKUP(Table16[[#This Row],[Movie_id]],'DAY 14'!$L$8:$N$18,2,FALSE) -> 200 | E10: =INDEX('DAY 14'!$M$9:$M$18,MATCH(A10,'DAY 14'!$L$9:$L$18,0)) -> 200 | F10: =IF(ISNA(C10),0, IF(C10=D10,1,-1)) -> 1 | L10: 103 | M10: 165 | N10: 644.8
A11: 103 | B11: Thor: The Dark World | C11: =VLOOKUP(Table16[[#This Row],[Movie_id]],'DAY 14'!$L$8:$N$18,2) -> 165 | D11: =VLOOKUP(Table16[[#This Row],[Movie_id]],'DAY 14'!$L$8:$N$18,2,FALSE) -> 165 | E11: =INDEX('DAY 14'!$M$9:$M$18,MATCH(A11,'DAY 14'!$L$9:$L$18,0)) -> 165 | F11: =IF(ISNA(C11),0, IF(C11=D11,1,-1)) -> 1 | L11: 105 | M11: 250 | N11: 670
A12: 104 | B12: Thor: Ragnarok | C12: =VLOOKUP(Table16[[#This Row],[Movie_id]],'DAY 14'!$L$8:$N$18,2) -> 165 | D12: =VLOOKUP(Table16[[#This Row],[Movie_id]],'DAY 14'!$L$8:$N$18,2,FALSE) -> 180 | E12: =INDEX('DAY 14'!$M$9:$M$18,MATCH(A12,'DAY 14'!$L$9:$L$18,0)) -> 180 | F12: =IF(ISNA(C12),0, IF(C12=D12,1,-1)) -> -1 | L12: 106
A13: 105 | B13: Thor: Love and Thunder | C13: =VLOOKUP(Table16[[#This Row],[Movie_id]],'DAY 14'!$L$8:$N$18,2) -> 250 | D13: =VLOOKUP(Table16[[#This Row],[Movie_id]],'DAY 14'!$L$8:$N$18,2,FALSE) -> 250 | E13: =INDEX('DAY 14'!$M$9:$M$18,MATCH(A13,'DAY 14'!$L$9:$L$18,0)) -> 250 | F13: =IF(ISNA(C13),0, IF(C13=D13,1,-1)) -> 1 | L13: 108 | M13: 550 | N13: 4000
A14: 106 | B14: Sholay | C14: =VLOOKUP(Table16[[#This Row],[Movie_id]],'DAY 14'!$L$8:$N$18,2) -> 0 | D14: =VLOOKUP(Table16[[#This Row],[Movie_id]],'DAY 14'!$L$8:$N$18,2,FALSE) -> 0 | E14: =INDEX('DAY 14'!$M$9:$M$18,MATCH(A14,'DAY 14'!$L$9:$L$18,0)) -> 0 | F14: =IF(ISNA(C14),0, IF(C14=D14,1,-1)) -> 1 | L14: 109 | M14: 390 | N14: 1360
A15: 107 | B15: Dilwale Dulhania Le Jayenge | C15: =VLOOKUP(Table16[[#This Row],[Movie_id]],'DAY 14'!$L$8:$N$18,2) -> 0 | D15: =VLOOKUP(Table16[[#This Row],[Movie_id]],'DAY 14'!$L$8:$N$18,2,FALSE) -> 400 | E15: =INDEX('DAY 14'!$M$9:$M$18,MATCH(A15,'DAY 14'!$L$9:$L$18,0)) -> 400 | F15: =IF(ISNA(C15),0, IF(C15=D15,1,-1)) -> -1 | L15: 110 | M15: 1 | N15: 3.5
A16: 108 | B16: 3 Idiots | C16: =VLOOKUP(Table16[[#This Row],[Movie_id]],'DAY 14'!$L$8:$N$18,2) -> 550 | D16: =VLOOKUP(Table16[[#This Row],[Movie_id]],'DAY 14'!$L$8:$N$18,2,FALSE) -> 550 | E16: =INDEX('DAY 14'!$M$9:$M$18,MATCH(A16,'DAY 14'!$L$9:$L$18,0)) -> 550 | F16: =IF(ISNA(C16),0, IF(C16=D16,1,-1)) -> 1 | L16: 104 | M16: 180 | N16: 854
A17: 109 | B17: Kabhi Khushi Kabhie Gham | C17: =VLOOKUP(Table16[[#This Row],[Movie_id]],'DAY 14'!$L$8:$N$18,2) -> 1 | D17: =VLOOKUP(Table16[[#This Row],[Movie_id]],'DAY 14'!$L$8:$N$18,2,FALSE) -> 390 | E17: =INDEX('DAY 14'!$M$9:$M$18,MATCH(A17,'DAY 14'!$L$9:$L$18,0)) -> 390 | F17: =IF(ISNA(C17),0, IF(C17=D17,1,-1)) -> -1 | L17: 107 | M17: 400 | N17: 2000
A18: 110 | B18: Bajirao Mastani | C18: =VLOOKUP(Table16[[#This Row],[Movie_id]],'DAY 14'!$L$8:$N$18,2) -> 1 | D18: =VLOOKUP(Table16[[#This Row],[Movie_id]],'DAY 14'!$L$8:$N$18,2,FALSE) -> 1 | E18: =INDEX('DAY 14'!$M$9:$M$18,MATCH(A18,'DAY 14'!$L$9:$L$18,0)) -> 1 | F18: =IF(ISNA(C18),0, IF(C18=D18,1,-1)) -> 1 | L18: 101 | M18: 1 | N18: 12.5

Sheet DAY 15
A1: EXCEL VS POWER BI
A4: Situation | F4: Excel | K4: POWERBI
A5: Small Datasets | F5: ✅ Best choice for small to medium datasets | L5: Not necessary
A6: Data Entry & Editing | F6: ✅ Easy manual entry and quick updates | L6: ❌ Not designed for data entry
A7: Formulas & Calculations | F7: ✅ Powerful formulas and what-if analysis | L7: DAX is powerful but focused on analytics
A8: Pivot Tables | F8: ✅ Fast and easy to create | L8: Available through visuals instead of Pivot Tables
A9: Large Datasets | F9: ❌ Performance decreases as data grows | L9: ✅ Optimized for millions of rows
A10: Interactive Dashboards | F10: Limited interactivity | L10: ✅ Rich interactive dashboards with drill-downs & slicers
A11: Automation & Refresh | F11: Manual refresh required | L11: ✅ Scheduled and automatic refresh
F12: File sharing through Excel | L12: ✅ Publish and share reports securely
A13: Scalability | F13: Best for personal or team analysis | L13: ✅ Built for enterprise reporting
A14: Best Use Case | F14: Analysis, calculations, financial modeling | L14: Business intelligence, dashboards, automated reporting
